Workbook
Name CF: OFFSET('AET NPV'!$B$63,0,0,1,'AET NPV'!$C$6)
Name CF: OFFSET(#REF!,0,0,1,#REF!)
Name CumDiscCF: OFFSET('AET NPV'!$B$66,0,0,1,VALUE('AET NPV'!$C$6))
Name CumDiscCF: OFFSET(#REF!,0,0,1,VALUE(#REF!))
Name Rev_Stream: 'M2'!$D$74:$D$81
Name Rev_Stream: #REF!
Name Revenue: 'M2'!$D$74:$E$81
Name Revenue: #REF!
Name scenario: #REF!

Sheet Sheet1
B3: Current | C3: Weight % | D3: LHV (kJ/kg) DAF | E3: Moisture Content % | F3: NCV (kJ/kg) AR
B4: Food/ Kitchen | C4: 0.2728 | D4: 25000 | E4: 0.35 | F4: =D4*(1-E4) -> 16250
B5: Garden | C5: 0.0072 | D5: 25000 | E5: 0.35 | F5: =D5*(1-E5) -> 16250
B6: Recycable Paper | C6: 0.0757 | D6: 25000 | E6: 0.35 | F6: =D6*(1-E6) -> 16250
B7: Recycable Metal | C7: 0.0282 | D7: 0 | E7: 0 | F7: =D7*(1-E7) -> 0
B8: Recycable Plastic | C8: 0.0461 | D8: 30000 | E8: 0.1 | F8: =D8*(1-E8) -> 27000
B9: Recycable Glass | C9: 0.0244 | D9: 0 | E9: 0 | F9: =D9*(1-E9) -> 0
B10: Other Fine Material | C10: 0.0544 | D10: 0 | E10: 0.25 | F10: =D10*(1-E10) -> 0
B11: Other putrescible | C11: 0.0601 | D11: 25000 | E11: 0.35 | F11: =D11*(1-E11) -> 16250
B12: Organic other | C12: 0.0883 | D12: 25000 | E12: 0.35 | F12: =D12*(1-E12) -> 16250
B13: Household Hazardous | C13: 0.0068 | D13: 25000 | E13: 0.35 | F13: =D13*(1-E13) -> 16250
B14: Others | C14: 0.0149 | D14: 25000 | E14: 0.35 | F14: =D14*(1-E14) -> 16250
B15: Non-Recyclable Paper | C15: 0.1338 | D15: 25000 | E15: 0.35 | F15: =D15*(1-E15) -> 16250
... B17: Non-Recylable Plastic | C17: 0.1637 | D17: 30000 | E17: 0.1 | F17: =D17*(1-E17) -> 27000
B18: Non-Recyclable Glass | C18: 0.003 | D18: 0 | E18: 0 | F18: =D18*(1-E18) -> 0 | J18: Feedstock Handling and Sorting | O18: Gasification | U18: Power Gen
C20: =SUM(C4:C18) -> 0.9999 | D20: =SUMPRODUCT(C4:C18,D4:D18) -> 22784 | E20: =SUMPRODUCT(C4:C18,E4:E18) -> 0.26544 | F20: =SUMPRODUCT(C4:C18,F4:F18) -> 16383.1 | J20: Annual Capacity | K20: 30000 | O20: Annual Capacity | P20: =(J40+J41)/1000*K20 -> 26082 | U20: Annual Capacity (kwh) | V20: 1000
J21: $/tonne annual cap | K21: 375 | O21: $/tonne annual cap | P21: 550 | U21: $/kwh | V21: 750
B22: Residual | C22: Weight % | D22: LHV (kJ/kg) DAF | E22: Moisture Content % | F22: NCV (kJ/kg) AR | J22: CAPEX | K22: =K20*K21 -> 11250000 | O22: CAPEX | P22: =P20*P21 -> 14345100 | U22: CAPEX | V22: =V20*V21 -> 750000
B23: Other Fine Material | C23: =100*C10/(100*SUM($C$10:$C$18)) -> 0.099725023 | D23: =D10 -> 0 | E23: =E10 -> 0.25 | F23: =F10 -> 0 | J23: Rate | K23: 0.12 | O23: Rate | P23: 0.08 | U23: Rate | V23: 0.08
B24: Other putrescible | C24: =100*C11/(100*SUM($C$10:$C$18)) -> 0.11017415 | D24: =D11 -> 25000 | E24: =E11 -> 0.35 | F24: =F11 -> 16250 | J24: Periods | K24: 15 | O24: Periods | P24: 15 | U24: Periods | V24: 15
B25: Organic other | C25: =100*C12/(100*SUM($C$10:$C$18)) -> 0.16186984 | D25: =D12 -> 25000 | E25: =E12 -> 0.35 | F25: =F12 -> 16250 | J25: PMT | K25: =PMT(K23,K24,K21*K20) -> -1651772.7 | L25: =K25/K20 -> -55.05909 | O25: PMT | P25: =PMT(P23,P24,P21*P20) -> -1675931.5 | U25: PMT | V25: =PMT(V23,V24,V21*V20) -> -87622.159
B26: Household Hazardous | C26: =100*C13/(100*SUM($C$10:$C$18)) -> 0.012465628 | D26: =D13 -> 25000 | E26: =E13 -> 0.35 | F26: =F13 -> 16250 | J26: PMT/kg | K26: =K25/(K20*1000) -> -0.05505909 | O26: PMT/kg | P26: =P25/(P20*1000) -> -0.06425625 | U26: PMT/kg | V26: =V25/(V20*1000) -> -0.087622159
B27: Others | C27: =100*C14/(100*SUM($C$10:$C$18)) -> 0.02731439 | D27: =D14 -> 25000 | E27: =E14 -> 0.35 | F27: =F14 -> 16250
B28: Non-Recyclable Paper | C28: =100*C15/(100*SUM($C$10:$C$18)) -> 0.24527956 | D28: =D15 -> 25000 | E28: =E15 -> 0.35 | F28: =F15 -> 16250 | J28: OPEX% of CAPEX | K28: 0.2 | O28: OPEX% of CAPEX | P28: 0.1 | U28: OPEX% of CAPEX | V28: 0.2
B29: Non-Recyclable Metal | C29: =100*C16/(100*SUM($C$10:$C$18)) -> 0.037580202 | D29: =D16 -> 0 | E29: =E16 -> 0 | F29: =F16 -> 0 | J29: OPEX | K29: =-K28*K22 -> -2250000 | L29: =K29/K20 -> -75 | O29: OPEX | P29: =-P28*P22 -> -1434510 | U29: OPEX | V29: =-V28*V22 -> -150000
B30: Non-Recylable Plastic | C30: =100*C17/(100*SUM($C$10:$C$18)) -> 0.30009166 | D30: =D17 -> 30000 | E30: =E17 -> 0.1 | F30: =F17 -> 27000 | J30: OPEX/kg | K30: =K29/(K20*1000) -> -0.075 | O30: OPEX/kg | P30: =P29/(P20*1000) -> -0.055 | U30: OPEX/kg | V30: =V29/(V20*1000) -> -0.15
B31: Non-Recyclable Glass | C31: =100*C18/(100*SUM($C$10:$C$18)) -> 0.0054995417 | D31: =D18 -> 0 | E31: =E18 -> 0 | F31: =F18 -> 0
A33: 1000 | B33: 0 | C33: =SUM(C23:C31) -> 1 | D33: =SUMPRODUCT(C23:C31,D23:D31) -> 22930.339 | E33: =SUMPRODUCT(C23:C31,E23:E31) -> 0.24992667 | F33: =SUMPRODUCT(C23:C31,F23:F31) -> 17155.408
P34: kg per Tonne | Q34: Value ($/kg) | R34: Total Value per Tonne | S34: Total Value
B35: Fines | C35: Weight | D35: LHV (kJ/kg) DAF | E35: Moisture Content % | F35: NCV (kJ/kg) AR | J35: Kg per Tonne | K35: Value ($/kg) | L35: Total Value per Tonne | M35: Total Value | O35: Light SRF | P35: =J40/SUM(J40:J41)*1000 -> 482.28663 | Q35: =-K40 -> 0.21316346 | R35: =P35*Q35 -> 102.80589 | S35: =R35*$P$20 -> 2681383.1 | U35: Energy/ Gas Gen (GJ)
B36: Other Fine Material | C36: =IF($B$33=0,$A$33*INDEX($C$4:$F$18,MATCH(B36,$B$4:$B$18,0),1),$A$33*IFERROR(INDEX($C$23:$F$31,MATCH(B36,$B$23:$B$31,0),1),0)) -> 54.4 | D36: =IFERROR(INDEX($D$4:$D$18,MATCH($B36,$B$4:$B$18,0)),0) -> 0 | E36: =IFERROR(INDEX($E$4:$E$18,MATCH($B36,$B$4:$B$18,0)),0) -> 0.25 | F36: =D36*(1-E36) -> 0 | I36: Gate Fee | J36: =1000 -> 1000 | K36: 0.2 | L36: =J36*K36 -> 200 | M36: =L36*$K$20 -> 6000000 | O36: Heacy SRF | P36: =J41/SUM(J40:J41)*1000 -> 517.71337 | Q36: =-K41 -> 0.1625 | R36: =P36*Q36 -> 84.128422 | S36: =R36*$P$20 -> 2194237.5
I37: Fines | J37: =C36 -> 54.4 | K37: -0.16 | L37: =J37*K37 -> -8.704 | M37: =L37*$K$20 -> -261120 | O37: Char | P37: =0.3*SUM(P35:P36) -> 300 | Q37: -0.16 | R37: =P37*Q37 -> -48 | S37: =R37*$P$20 -> -1251936
B38: Metals | C38: Weight | D38: LHV (kJ/kg) DAF | E38: Moisture Content % | F38: NCV (kJ/kg) AR | I38: Metals | J38: =SUM(C39:C40) -> 48.7 | K38: 0.2 | L38: =J38*K38 -> 9.74 | M38: =L38*$K$20 -> 292200 | O38: Energy/ Gas Gen (GJ) | P38: =(P35*F52/1000/1000+P36*F61/1000/1000)*0.7 -> 13.085402 | Q38: 10 | R38: =P38*Q38 -> 130.85402 | S38: =R38*$P$20 -> 3412934.5
B39: Recycable Metal | C39: =IF($B$33=0,$A$33*INDEX($C$4:$F$18,MATCH(B39,$B$4:$B$18,0),1),$A$33*IFERROR(INDEX($C$23:$F$31,MATCH(B39,$B$23:$B$31,0),1),0)) -> 28.2 | D39: =IFERROR(INDEX($D$4:$D$18,MATCH($B39,$B$4:$B$18,0)),0) -> 0 | E39: =IFERROR(INDEX($E$4:$E$18,MATCH($B39,$B$4:$B$18,0)),0) -> 0 | F39: =D39*(1-E39) -> 0 | I39: Glass | J39: =SUM(C43:C44) -> 27.4 | K39: 0.03 | L39: =J39*K39 -> 0.822 | M39: =L39*$K$20 -> 24660 | O39: CO2 | P39: 1000 | Q39: 0.015 | R39: =P39*Q39 -> 15 | S39: =R39*$P$20 -> 391230
B40: Non-Recyclable Metal | C40: =IF($B$33=0,$A$33*INDEX($C$4:$F$18,MATCH(B40,$B$4:$B$18,0),1),$A$33*IFERROR(INDEX($C$23:$F$31,MATCH(B40,$B$23:$B$31,0),1),0)) -> 20.5 | D40: =IFERROR(INDEX($D$4:$D$18,MATCH($B40,$B$4:$B$18,0)),0) -> 0 | E40: =IFERROR(INDEX($E$4:$E$18,MATCH($B40,$B$4:$B$18,0)),0) -> 0 | F40: =D40*(1-E40) -> 0 | I40: Light SRF | J40: =SUM(C48:C51) -> 419.3 | K40: =G52 -> -0.21316346 | L40: =J40*K40 -> -89.379438 | M40: =L40*$K$20 -> -2681383.1 | O40: Total Value per Tonne of Feed | P40: 1000 | Q40: =R40/P40 -> 0.28478833 | R40: =SUM(R35:R39) -> 284.78833 | S40: =R40*$P$20 -> 7427849.1
I41: Heavy SRF | J41: =SUM(C55:C60) -> 450.1 | K41: =G61 -> -0.1625 | L41: =J41*K41 -> -73.14125 | M41: =L41*$K$20 -> -2194237.5 | O41: CAPEX | P41: 1000 | Q41: =P26 -> -0.06425625 | R41: =P41*Q41 -> -64.25625 | S41: =R41*$P$20 -> -1675931.5
B42: Glass | I42: Avg Prod Value | J42: 1000 | K42: =SUMPRODUCT(J37:J41,K37:K41)/J42 -> -0.16066269 | L42: =J42*K42 -> -160.66269 | M42: =L42*$K$20 -> -4819880.6 | O42: OPEX | P42: 1000 | Q42: =P30 -> -0.055 | R42: =P42*Q42 -> -55 | S42: =R42*$P$20 -> -1434510
B43: Recycable Glass | C43: =IF($B$33=0,$A$33*INDEX($C$4:$F$18,MATCH(B43,$B$4:$B$18,0),1),$A$33*IFERROR(INDEX($C$23:$F$31,MATCH(B43,$B$23:$B$31,0),1),0)) -> 24.4 | D43: =IFERROR(INDEX($D$4:$D$18,MATCH($B43,$B$4:$B$18,0)),0) -> 0 | E43: =IFERROR(INDEX($E$4:$E$18,MATCH($B43,$B$4:$B$18,0)),0) -> 0 | F43: =D43*(1-E43) -> 0 | I43: Total Value per Tonne of Feed | J43: 1000 | K43: =K36+K42 -> 0.039337312 | L43: =J43*K43 -> 39.337312 | M43: =L43*$K$20 -> 1180119.4 | O43: Margin | P43: 1000 | Q43: =Q40+Q41+Q42 -> 0.16553208 | R43: =P43*Q43 -> 165.53208 | S43: =R43*$P$20 -> 4317407.6
B44: Non-Recyclable Glass | C44: =IF($B$33=0,$A$33*INDEX($C$4:$F$18,MATCH(B44,$B$4:$B$18,0),1),$A$33*IFERROR(INDEX($C$23:$F$31,MATCH(B44,$B$23:$B$31,0),1),0)) -> 3 | D44: =IFERROR(INDEX($D$4:$D$18,MATCH($B44,$B$4:$B$18,0)),0) -> 0 | E44: =IFERROR(INDEX($E$4:$E$18,MATCH($B44,$B$4:$B$18,0)),0) -> 0 | F44: =D44*(1-E44) -> 0 | I44: CAPEX | J44: 1000 | K44: =K26 -> -0.05505909 | L44: =J44*K44 -> -55.05909 | M44: =L44*$K$20 -> -1651772.7
I45: OPEX | J45: 1000 | K45: =K30 -> -0.075 | L45: =J45*K45 -> -75 | M45: =L45*$K$20 -> -2250000
I46: Margin | J46: 1000 | K46: =K43+K44+K45 -> -0.090721778 | L46: =J46*K46 -> -90.721778 | M46: =M43+M44+M45 -> -2721653.3
B47: Light SRF | C47: Weight | D47: LHV (kJ/kg) DAF | E47: Moisture Content % | F47: NCV (kJ/kg) AR | G47: $/kg
B48: Recycable Paper | C48: =IF($B$33=0,$A$33*INDEX($C$4:$F$18,MATCH(B48,$B$4:$B$18,0),1),$A$33*IFERROR(INDEX($C$23:$F$31,MATCH(B48,$B$23:$B$31,0),1),0)) -> 75.7 | D48: =IFERROR(INDEX($D$4:$D$18,MATCH($B48,$B$4:$B$18,0)),0) -> 25000 | E48: =IFERROR(INDEX($E$4:$E$18,MATCH($B48,$B$4:$B$18,0)),0) -> 0.35 | F48: =D48*(1-E48) -> 16250 | I48: Base $/GJ
B49: Recycable Plastic | C49: =IF($B$33=0,$A$33*INDEX($C$4:$F$18,MATCH(B49,$B$4:$B$18,0),1),$A$33*IFERROR(INDEX($C$23:$F$31,MATCH(B49,$B$23:$B$31,0),1),0)) -> 46.1 | D49: =IFERROR(INDEX($D$4:$D$18,MATCH($B49,$B$4:$B$18,0)),0) -> 30000 | E49: =IFERROR(INDEX($E$4:$E$18,MATCH($B49,$B$4:$B$18,0)),0) -> 0.1 | F49: =D49*(1-E49) -> 27000 | I49: 10
B50: Non-Recyclable Paper | C50: =IF($B$33=0,$A$33*INDEX($C$4:$F$18,MATCH(B50,$B$4:$B$18,0),1),$A$33*IFERROR(INDEX($C$23:$F$31,MATCH(B50,$B$23:$B$31,0),1),0)) -> 133.8 | D50: =IFERROR(INDEX($D$4:$D$18,MATCH($B50,$B$4:$B$18,0)),0) -> 25000 | E50: =IFERROR(INDEX($E$4:$E$18,MATCH($B50,$B$4:$B$18,0)),0) -> 0.35 | F50: =D50*(1-E50) -> 16250 | I50: LSRF Discount | J50: LSRF $/GJ
B51: Non-Recylable Plastic | C51: =IF($B$33=0,$A$33*INDEX($C$4:$F$18,MATCH(B51,$B$4:$B$18,0),1),$A$33*IFERROR(INDEX($C$23:$F$31,MATCH(B51,$B$23:$B$31,0),1),0)) -> 163.7 | D51: =IFERROR(INDEX($D$4:$D$18,MATCH($B51,$B$4:$B$18,0)),0) -> 30000 | E51: =IFERROR(INDEX($E$4:$E$18,MATCH($B51,$B$4:$B$18,0)),0) -> 0.1 | F51: =D51*(1-E51) -> 27000 | I51: 2 | J51: =I49*(1-I51) -> -10
C52: =SUM(C48:C51) -> 419.3 | D52: =SUMPRODUCT(C48:C51,D48:D51)/C52 -> 27501.789 | E52: =SUMPRODUCT(C48:C51,E48:E51)/C52 -> 0.22491057 | F52: =D52*(1-E52) -> 21316.346 | G52: =F52/1000/1000*J51 -> -0.21316346 | I52: HSRF Discount | J52: HSRF $/GJ | P52: 100 | Q52: 150
I53: 2 | J53: =I49*(1-I53) -> -10
B54: Heavy SRF | C54: Weight | D54: LHV (kJ/kg) DAF | E54: Moisture Content % | F54: NCV (kJ/kg) AR | G54: $/kg
B55: Food/ Kitchen | C55: =IF($B$33=0,$A$33*INDEX($C$4:$F$18,MATCH(B55,$B$4:$B$18,0),1),$A$33*IFERROR(INDEX($C$23:$F$31,MATCH(B55,$B$23:$B$31,0),1),0)) -> 272.8 | D55: =IFERROR(INDEX($D$4:$D$18,MATCH($B55,$B$4:$B$18,0)),0) -> 25000 | E55: =IFERROR(INDEX($E$4:$E$18,MATCH($B55,$B$4:$B$18,0)),0) -> 0.35 | F55: =D55*(1-E55) -> 16250
B56: Garden | C56: =IF($B$33=0,$A$33*INDEX($C$4:$F$18,MATCH(B56,$B$4:$B$18,0),1),$A$33*IFERROR(INDEX($C$23:$F$31,MATCH(B56,$B$23:$B$31,0),1),0)) -> 7.2 | D56: =IFERROR(INDEX($D$4:$D$18,MATCH($B56,$B$4:$B$18,0)),0) -> 25000 | E56: =IFERROR(INDEX($E$4:$E$18,MATCH($B56,$B$4:$B$18,0)),0) -> 0.35 | F56: =D56*(1-E56) -> 16250
B57: Other putrescible | C57: =IF($B$33=0,$A$33*INDEX($C$4:$F$18,MATCH(B57,$B$4:$B$18,0),1),$A$33*IFERROR(INDEX($C$23:$F$31,MATCH(B57,$B$23:$B$31,0),1),0)) -> 60.1 | D57: =IFERROR(INDEX($D$4:$D$18,MATCH($B57,$B$4:$B$18,0)),0) -> 25000 | E57: =IFERROR(INDEX($E$4:$E$18,MATCH($B57,$B$4:$B$18,0)),0) -> 0.35 | F57: =D57*(1-E57) -> 16250
B58: Organic other | C58: =IF($B$33=0,$A$33*INDEX($C$4:$F$18,MATCH(B58,$B$4:$B$18,0),1),$A$33*IFERROR(INDEX($C$23:$F$31,MATCH(B58,$B$23:$B$31,0),1),0)) -> 88.3 | D58: =IFERROR(INDEX($D$4:$D$18,MATCH($B58,$B$4:$B$18,0)),0) -> 25000 | E58: =IFERROR(INDEX($E$4:$E$18,MATCH($B58,$B$4:$B$18,0)),0) -> 0.35 | F58: =D58*(1-E58) -> 16250
B59: Household Hazardous | C59: =IF($B$33=0,$A$33*INDEX($C$4:$F$18,MATCH(B59,$B$4:$B$18,0),1),$A$33*IFERROR(INDEX($C$23:$F$31,MATCH(B59,$B$23:$B$31,0),1),0)) -> 6.8 | D59: =IFERROR(INDEX($D$4:$D$18,MATCH($B59,$B$4:$B$18,0)),0) -> 25000 | E59: =IFERROR(INDEX($E$4:$E$18,MATCH($B59,$B$4:$B$18,0)),0) -> 0.35 | F59: =D59*(1-E59) -> 16250
B60: Others | C60: =IF($B$33=0,$A$33*INDEX($C$4:$F$18,MATCH(B60,$B$4:$B$18,0),1),$A$33*IFERROR(INDEX($C$23:$F$31,MATCH(B60,$B$23:$B$31,0),1),0)) -> 14.9 | D60: =IFERROR(INDEX($D$4:$D$18,MATCH($B60,$B$4:$B$18,0)),0) -> 25000 | E60: =IFERROR(INDEX($E$4:$E$18,MATCH($B60,$B$4:$B$18,0)),0) -> 0.35 | F60: =D60*(1-E60) -> 16250
C61: =SUM(C55:C60) -> 450.1 | D61: =SUMPRODUCT(C55:C60,D55:D60)/C61 -> 25000 | E61: =SUMPRODUCT(C55:C60,E55:E60)/C61 -> 0.35 | F61: =D61*(1-E61) -> 16250 | G61: =F61/1000/1000*J53 -> -0.1625
B67: =12*15*6 -> 1080 | C67: =15*6*30 -> 2700 | E67: =64*1000*1000/3600/1000*0.2 -> 3.5555556
B68: =B67*30 -> 32400
B70: =753*2700 -> 2033100
B71: =B70*0.33 -> 670923

Sheet Sheet3
D4: Low Case ($/T) | E4: High Case ($/T)
C5: CAPEX | D5: -150 | E5: -110 | F5: =E5-D5 -> 40
C6: OPEX | D6: -110 | E6: -90 | F6: =E6-D6 -> 20
C7: Recovered Material | D7: -5 | E7: 11 | F7: =E7-D7 -> 16
C8: CO2 linked to Energy | D8: 0 | E8: =45000*16/30000 -> 24 | F8: =E8-D8 -> 24
C9: Char | D9: -30 | E9: 10 | F9: =E9-D9 -> 40
C10: Gate Fee* CPI Adj | D10: 165 | E10: 165
C11: CAPEX Savings | D11: 40
C12: OPEX Savings | D12: 20
C13: Imprv. Recovered Material Markets | D13: 16
C14: CO2 Credits Obtained | D14: 45
C15: Imprv. Char Markets | D15: 40
C18: Marigin | D18: =SUM(D5:D10) -> -130 | E18: =SUM(E5:E10) -> 10
D22: =165/295 -> 0.55932203 | E22: =165/200 -> 0.825

Sheet AET NPV
A1: Equity Analysis of a Project
E2: INPUT SHEET: USER ENTERS ALL BOLD NUMBERS
A3: INITIAL INVESTMENT | E3: CASHFLOW DETAILS | I3: DISCOUNT RATE
A4: Initial Investment= | C4: =Sheet1!K22 -> 11250000 | E4: Tax rate on net income= | G4: 0.3 | I4: Approach(1:Direct;2:CAPM)= | K4: 1
A5: Opportunity cost (if any)= | C5: 0 | I5: 1. Discount rate = | K5: 0.12
A6: Lifetime of the investment | C6: =Sheet1!K24 -> 15 | I6: 2a. Beta | K6: 1
A7: Salvage Value at end of project= | C7: 0 | I7: b. Riskless rate= | K7: 0.04
A8: Deprec. method(1:St.line;2:DDB)= | C8: 1 | I8: c. Market risk premium = | K8: 0.08
A9: Tax Credit (if any )= | C9: 0 | I9: d. Debt Ratio = | K9: 0.5
A10: Other invest.(non-depreciable)= | C10: 0 | I10: e. Cost of Borrowing = | K10: 0.08
I11: Discount rate used= | K11: =IF(K4=1,K5,(K7+K6*K8)*(1-K9)+K10*(1-G4)*K9) -> 0.12
A12: WORKING CAPITAL
A13: Initial Investment in Work. Cap= | C13: 0
A14: Working Capital as % of Rev= | C14: 0
A15: Salvageable fraction at end= | C15: 0
A17: GROWTH RATES
C18: 1 | D18: 2 | E18: 3 | F18: 4 | G18: 5 | H18: 6 | I18: 7 | J18: 8 | K18: 9 | L18: 10 | M18: 11 | N18: 12 | O18: 13 | P18: 14 | Q18: 15 | R18: 16 | S18: 17 | T18: 18 | U18: 19 | V18: 20
A19: Revenues | C19: Do not enter | D19: =(D46/C46)-1 -> 0.12710579 | E19: =(E46/D46)-1 -> 0.11559113 | F19: =(F46/E46)-1 -> 0.1062046 | G19: =(G46/F46)-1 -> 0.0984083 | H19: =(H46/G46)-1 -> 0.091831523 | I19: =(I46/H46)-1 -> 0.086210473 | J19: =(J46/I46)-1 -> 0.081352313 | K19: =(K46/J46)-1 -> 0.077112815 | ... V19: =(V46/U46)-1 -> #DIV/0!
A20: +Gate Fee | D20: 0.025 | E20: =D20 -> 0.025 | F20: =E20 -> 0.025 | G20: =F20 -> 0.025 | H20: =G20 -> 0.025 | I20: =H20 -> 0.025 | J20: =I20 -> 0.025 | K20: =J20 -> 0.025 | L20: =K20 -> 0.025 | ... V20: =U20 -> 0.025
A21: +Recycable Material | D21: 0 | E21: =D21 -> 0 | F21: =E21 -> 0 | G21: =F21 -> 0 | H21: =G21 -> 0 | I21: =H21 -> 0 | J21: =I21 -> 0 | K21: =J21 -> 0 | L21: =K21 -> 0 | ... V21: =U21 -> 0
A22: +Energy | D22: 0 | E22: =D22 -> 0 | F22: =E22 -> 0 | G22: =F22 -> 0 | H22: =G22 -> 0 | I22: =H22 -> 0 | J22: =I22 -> 0 | K22: =J22 -> 0 | L22: =K22 -> 0 | ... V22: =U22 -> 0
A23: +Other | D23: 0 | E23: =D23 -> 0 | F23: =E23 -> 0 | G23: =F23 -> 0 | H23: =G23 -> 0 | I23: =H23 -> 0 | J23: =I23 -> 0 | K23: =J23 -> 0 | L23: =K23 -> 0 | ... V23: =U23 -> 0
A24: Operating Expenses | C24: Do not enter | D24: =(D51/C51)-1 -> 0.025 | E24: =(E51/D51)-1 -> 0.025 | F24: =(F51/E51)-1 -> 0.025 | G24: =(G51/F51)-1 -> 0.025 | H24: =(H51/G51)-1 -> 0.025 | I24: =(I51/H51)-1 -> 0.025 | J24: =(J51/I51)-1 -> 0.025 | K24: =(K51/J51)-1 -> 0.025 | ... V24: =(V51/U51)-1 -> #DIV/0!
A25: -O&M Variable | D25: 0.025 | E25: =D25 -> 0.025 | F25: =E25 -> 0.025 | G25: =F25 -> 0.025 | H25: =G25 -> 0.025 | I25: =H25 -> 0.025 | J25: =I25 -> 0.025 | K25: =J25 -> 0.025 | L25: =K25 -> 0.025 | ... V25: =U25 -> 0.025
A26: -O&M Fixed | D26: 0.025 | E26: =D26 -> 0.025 | F26: =E26 -> 0.025 | G26: =F26 -> 0.025 | H26: =G26 -> 0.025 | I26: =H26 -> 0.025 | J26: =I26 -> 0.025 | K26: =J26 -> 0.025 | L26: =K26 -> 0.025 | ... V26: =U26 -> 0.025
A27: -Other | D27: 0 | E27: =D27 -> 0 | F27: =E27 -> 0 | G27: =F27 -> 0 | H27: =G27 -> 0 | I27: =H27 -> 0 | J27: =I27 -> 0 | K27: =J27 -> 0 | L27: =K27 -> 0 | ... V27: =U27 -> 0
F29: YEAR
B30: 0 | C30: 1 | D30: 2 | E30: 3 | F30: 4 | G30: 5 | H30: 6 | I30: 7 | J30: 8 | K30: 9 | L30: 10 | M30: 11 | N30: 12 | O30: 13 | P30: 14 | Q30: 15 | R30: 16 | S30: 17 | T30: 18 | U30: 19 | V30: 20
A31: INVESTMENTS
A32: Investment | B32: =C4 -> 11250000
A33: - Tax Credit | B33: =C4*C9 -> 0
A34: Net Investment | B34: =B32-B33 -> 11250000
A35: + Working Cap | B35: =C13 -> 0
A36: + Opp. Cost | B36: =C5 -> 0
A37: + Other invest. | B37: =C10 -> 0
A38: Investments | B38: =B34+B35+B36+B37 -> 11250000
A40: SALVAGE VALUE
A41: Equipment | C41: =IF(C30=$C$6,$C$7,0) -> 0 | D41: =IF(D30=$C$6,$C$7,0) -> 0 | E41: =IF(E30=$C$6,$C$7,0) -> 0 | F41: =IF(F30=$C$6,$C$7,0) -> 0 | G41: =IF(G30=$C$6,$C$7,0) -> 0 | H41: =IF(H30=$C$6,$C$7,0) -> 0 | I41: =IF(I30=$C$6,$C$7,0) -> 0 | J41: =IF(J30=$C$6,$C$7,0) -> 0 | ... V41: =IF(V30=$C$6,$C$7,0) -> 0
A42: Working Capital | C42: =IF(C30=$C$6,($C$13+SUM($C$61:$V$61))*$C$15,0) -> 0 | D42: =IF(D30=$C$6,($C$13+SUM($C$61:$V$61))*$C$15,0) -> 0 | E42: =IF(E30=$C$6,($C$13+SUM($C$61:$V$61))*$C$15,0) -> 0 | F42: =IF(F30=$C$6,($C$13+SUM($C$61:$V$61))*$C$15,0) -> 0 | G42: =IF(G30=$C$6,($C$13+SUM($C$61:$V$61))*$C$15,0) -> 0 | H42: =IF(H30=$C$6,($C$13+SUM($C$61:$V$61))*$C$15,0) -> 0 | I42: =IF(I30=$C$6,($C$13+SUM($C$61:$V$61))*$C$15,0) -> 0 | J42: =IF(J30=$C$6,($C$13+SUM($C$61:$V$61))*$C$15,0) -> 0 | ... V42: =IF(V30=$C$6,($C$13+SUM($C$61:$V$61))*$C$15,0) -> 0
A44: OPERATING CASHFLOWS
A45: Lifetime Index | C45: =IF(C30>$C$6,0,1) -> 1 | D45: =IF(D30>$C$6,0,1) -> 1 | E45: =IF(E30>$C$6,0,1) -> 1 | F45: =IF(F30>$C$6,0,1) -> 1 | G45: =IF(G30>$C$6,0,1) -> 1 | H45: =IF(H30>$C$6,0,1) -> 1 | I45: =IF(I30>$C$6,0,1) -> 1 | J45: =IF(J30>$C$6,0,1) -> 1 | ... V45: =IF(V30>$C$6,0,1) -> 0
A46: Revenues | C46: =SUM(C47:C50) -> 1180119.4 | D46: =SUM(D47:D50) -> 1330119.4 | E46: =SUM(E47:E50) -> 1483869.4 | F46: =SUM(F47:F50) -> 1641463.1 | G46: =SUM(G47:G50) -> 1802996.7 | H46: =SUM(H47:H50) -> 1968568.6 | I46: =SUM(I47:I50) -> 2138279.9 | J46: =SUM(J47:J50) -> 2312233.9 | ... V46: =SUM(V47:V50) -> 0
A47: +Gate Fee | C47: =Sheet1!M36 -> 6000000 | D47: =C47*(1+D20)*D$45 -> 6150000 | E47: =D47*(1+E20)*E$45 -> 6303750 | F47: =E47*(1+F20)*F$45 -> 6461343.7 | G47: =F47*(1+G20)*G$45 -> 6622877.3 | H47: =G47*(1+H20)*H$45 -> 6788449.3 | I47: =H47*(1+I20)*I$45 -> 6958160.5 | J47: =I47*(1+J20)*J$45 -> 7132114.5 | K47: =J47*(1+K20)*K$45 -> 7310417.4 | ... V47: =U47*(1+V20)*V$45 -> 0
A48: +Recycable | C48: =SUM(Sheet1!M37:M39) -> 55740 | D48: =C48*(1+D21)*D$45 -> 55740 | E48: =D48*(1+E21)*E$45 -> 55740 | F48: =E48*(1+F21)*F$45 -> 55740 | G48: =F48*(1+G21)*G$45 -> 55740 | H48: =G48*(1+H21)*H$45 -> 55740 | I48: =H48*(1+I21)*I$45 -> 55740 | J48: =I48*(1+J21)*J$45 -> 55740 | K48: =J48*(1+K21)*K$45 -> 55740 | ... V48: =U48*(1+V21)*V$45 -> 0
A49: +Energy | C49: =SUM(Sheet1!M40:M41) -> -4875620.6 | D49: =C49*(1+D22)*D$45 -> -4875620.6 | E49: =D49*(1+E22)*E$45 -> -4875620.6 | F49: =E49*(1+F22)*F$45 -> -4875620.6 | G49: =F49*(1+G22)*G$45 -> -4875620.6 | H49: =G49*(1+H22)*H$45 -> -4875620.6 | I49: =H49*(1+I22)*I$45 -> -4875620.6 | J49: =I49*(1+J22)*J$45 -> -4875620.6 | K49: =J49*(1+K22)*K$45 -> -4875620.6 | ... V49: =U49*(1+V22)*V$45 -> 0
A50: +Other | C50: 0 | D50: =C50*(1+D23)*D$45 -> 0 | E50: =D50*(1+E23)*E$45 -> 0 | F50: =E50*(1+F23)*F$45 -> 0 | G50: =F50*(1+G23)*G$45 -> 0 | H50: =G50*(1+H23)*H$45 -> 0 | I50: =H50*(1+I23)*I$45 -> 0 | J50: =I50*(1+J23)*J$45 -> 0 | K50: =J50*(1+K23)*K$45 -> 0 | ... V50: =U50*(1+V23)*V$45 -> 0
A51: Operating Expenses | C51: =SUM(C52:C54) -> 2250000 | D51: =SUM(D52:D54) -> 2306250 | E51: =SUM(E52:E54) -> 2363906.2 | F51: =SUM(F52:F54) -> 2423003.9 | G51: =SUM(G52:G54) -> 2483579 | H51: =SUM(H52:H54) -> 2545668.5 | I51: =SUM(I52:I54) -> 2609310.2 | J51: =SUM(J52:J54) -> 2674542.9 | ... V51: =SUM(V52:V54) -> 0
A52: -O&M Variable | C52: =-Sheet1!M45 -> 2250000 | D52: =C52*(1+D25)*D$45 -> 2306250 | E52: =D52*(1+E25)*E$45 -> 2363906.2 | F52: =E52*(1+F25)*F$45 -> 2423003.9 | G52: =F52*(1+G25)*G$45 -> 2483579 | H52: =G52*(1+H25)*H$45 -> 2545668.5 | I52: =H52*(1+I25)*I$45 -> 2609310.2 | J52: =I52*(1+J25)*J$45 -> 2674542.9 | K52: =J52*(1+K25)*K$45 -> 2741406.5 | ... V52: =U52*(1+V25)*V$45 -> 0
A53: -O&M Fixed | C53: 0 | D53: =C53*(1+D26)*D$45 -> 0 | E53: =D53*(1+E26)*E$45 -> 0 | F53: =E53*(1+F26)*F$45 -> 0 | G53: =F53*(1+G26)*G$45 -> 0 | H53: =G53*(1+H26)*H$45 -> 0 | I53: =H53*(1+I26)*I$45 -> 0 | J53: =I53*(1+J26)*J$45 -> 0 | K53: =J53*(1+K26)*K$45 -> 0 | ... V53: =U53*(1+V26)*V$45 -> 0
A54: -Other | C54: 0 | D54: =C54*(1+D27)*D$45 -> 0 | E54: =D54*(1+E27)*E$45 -> 0 | F54: =E54*(1+F27)*F$45 -> 0 | G54: =F54*(1+G27)*G$45 -> 0 | H54: =G54*(1+H27)*H$45 -> 0 | I54: =H54*(1+I27)*I$45 -> 0 | J54: =I54*(1+J27)*J$45 -> 0 | K54: =J54*(1+K27)*K$45 -> 0 | ... V54: =U54*(1+V27)*V$45 -> 0
A55: EBITDA | C55: =C46-C51 -> -1069880.6 | D55: =D46-D51 -> -976130.65 | E55: =E46-E51 -> -880036.9 | F55: =F46-F51 -> -781540.8 | G55: =G46-G51 -> -680582.31 | H55: =H46-H51 -> -577099.85 | I55: =I46-I51 -> -471030.33 | J55: =J46-J51 -> -362309.07 | ... V55: =V46-V51 -> 0
A56: - Depreciation | C56: =C76 -> 750000 | D56: =D76 -> 750000 | E56: =E76 -> 750000 | F56: =F76 -> 750000 | G56: =G76 -> 750000 | H56: =H76 -> 750000 | I56: =I76 -> 750000 | J56: =J76 -> 750000 | ... V56: =V76 -> 0
A57: EBIT | C57: =C55-C56 -> -1819880.6 | D57: =D55-D56 -> -1726130.6 | E57: =E55-E56 -> -1630036.9 | F57: =F55-F56 -> -1531540.8 | G57: =G55-G56 -> -1430582.3 | H57: =H55-H56 -> -1327099.8 | I57: =I55-I56 -> -1221030.3 | J57: =J55-J56 -> -1112309.1 | ... V57: =V55-V56 -> 0
A58: -Tax | C58: =C57*$G$4 -> -545964.19 | D58: =D57*$G$4 -> -517839.19 | E58: =E57*$G$4 -> -489011.07 | F58: =F57*$G$4 -> -459462.24 | G58: =G57*$G$4 -> -429174.69 | H58: =H57*$G$4 -> -398129.95 | I58: =I57*$G$4 -> -366309.1 | J58: =J57*$G$4 -> -333692.72 | ... V58: =V57*$G$4 -> 0
A59: EBT(1-t) | C59: =C57-C58 -> -1273916.5 | D59: =D57-D58 -> -1208291.5 | E59: =E57-E58 -> -1141025.8 | F59: =F57-F58 -> -1072078.6 | G59: =G57-G58 -> -1001407.6 | H59: =H57-H58 -> -928969.89 | I59: =I57-I58 -> -854721.23 | J59: =J57-J58 -> -778616.35 | ... V59: =V57-V58 -> 0
A60: + Depreciation | C60: =C56 -> 750000 | D60: =D56 -> 750000 | E60: =E56 -> 750000 | F60: =F56 -> 750000 | G60: =G56 -> 750000 | H60: =H56 -> 750000 | I60: =I56 -> 750000 | J60: =J56 -> 750000 | ... V60: =V56 -> 0
A61: - ∂ Work. Cap | C61: =(C14*C46-B35)*C45 -> 0 | D61: =($C$14*D46-$B$35)*D45 -> 0 | E61: =($C$14*E46-$B$35)*E45 -> 0 | F61: =($C$14*F46-$B$35)*F45 -> 0 | G61: =($C$14*G46-$B$35)*G45 -> 0 | H61: =($C$14*H46-$B$35)*H45 -> 0 | I61: =($C$14*I46-$B$35)*I45 -> 0 | J61: =($C$14*J46-$B$35)*J45 -> 0 | K61: =($C$14*K46-$B$35)*K45 -> 0 | ... V61: =($C$14*V46-$B$35)*V45 -> 0
A62: Capital Investment | B62: =-B38 -> -11250000
A63: NATCF | B63: =B62+B59+B60-B61 -> -11250000 | C63: =C62+C59+C60-C61 -> -523916.45 | D63: =D62+D59+D60-D61 -> -458291.45 | E63: =E62+E59+E60-E61 -> -391025.83 | F63: =F62+F59+F60-F61 -> -322078.56 | G63: =G62+G59+G60-G61 -> -251407.61 | H63: =H62+H59+H60-H61 -> -178969.89 | I63: =I62+I59+I60-I61 -> -104721.23 | ... V63: =V62+V59+V60-V61 -> 0
A64: Discount Factor | B64: =1 -> 1 | C64: =C45*(1+$K$11)^C30 -> 1.12 | D64: =D45*(1+$K$11)^D30 -> 1.2544 | E64: =E45*(1+$K$11)^E30 -> 1.404928 | F64: =F45*(1+$K$11)^F30 -> 1.5735194 | G64: =G45*(1+$K$11)^G30 -> 1.7623417 | H64: =H45*(1+$K$11)^H30 -> 1.9738227 | I64: =I45*(1+$K$11)^I30 -> 2.2106814 | J64: =J45*(1+$K$11)^J30 -> 2.4759632 | ... V64: =V45*(1+$K$11)^V30 -> 0
A65: Discounted CF | B65: =0-B38 -> -11250000 | C65: =(C63+C41+C42)/(1+$K$11)^C30 -> -467782.55 | D65: =(D63+D41+D42)/(1+$K$11)^D30 -> -365347.14 | E65: =(E63+E41+E42)/(1+$K$11)^E30 -> -278324.46 | F65: =(F63+F41+F42)/(1+$K$11)^F30 -> -204686.75 | G65: =(G63+G41+G42)/(1+$K$11)^G30 -> -142655.43 | H65: =(H63+H41+H42)/(1+$K$11)^H30 -> -90671.717 | I65: =(I63+I41+I42)/(1+$K$11)^I30 -> -47370.566 | J65: =(J63+J41+J42)/(1+$K$11)^J30 -> -11557.663 | ... V65: =(V63+V41+V42)/(1+$K$11)^V30 -> 0
A66: Cumulative CF | B66: =B65 -> -11250000 | C66: =B66+C65 -> -11717783 | D66: =C66+D65 -> -12083130 | E66: =D66+E65 -> -12361454 | F66: =E66+F65 -> -12566141 | G66: =F66+G65 -> -12708796 | H66: =G66+H65 -> -12799468 | I66: =H66+I65 -> -12846839 | J66: =I66+J65 -> -12858396 | ... V66: =U66+V65 -> -12376543
B68: Investment Measures
B69: NPV = | C69: =SUM(B65:V65) -> -12376543
B70: IRR = | C70: =IRR(B63:V63,K11) -> -0.13730022
B71: ROC = | C71: =SUM(C59:V59)/SUM(B77:V77) -> -0.12680488
E74: BOOK VALUE & DEPRECIATION
A75: Book Value (beginning) | C75: =C4 -> 11250000 | D75: =(C75-C76)*D45 -> 10500000 | E75: =(D75-D76)*E45 -> 9750000 | F75: =(E75-E76)*F45 -> 9000000 | G75: =(F75-F76)*G45 -> 8250000 | H75: =(G75-G76)*H45 -> 7500000 | I75: =(H75-H76)*I45 -> 6750000 | J75: =(I75-I76)*J45 -> 6000000 | K75: =(J75-J76)*K45 -> 5250000 | ... V75: =(U75-U76)*V45 -> 0
A76: Depreciation | C76: =IF($C$8=1,(($C$4-$C$7)/$C$6)*C45,(IF($C$7<$C$4*(1-2/$C$6)^(C30),$C$4*(1-2/$C$6)^(C30-1)*(2/$C$6)*C45,(IF(0>($C$4*(1-2/$C$6)^(C30-1))-$C$7,0,$C$4*C45*(1-2/$C$6)^(C30-1)-$C$7))))) -> 750000 | D76: =IF($C$8=1,(($C$4-$C$7)/$C$6)*D45,(IF($C$7<$C$4*(1-2/$C$6)^(D30),$C$4*(1-2/$C$6)^(D30-1)*(2/$C$6)*D45,(IF(0>($C$4*(1-2/$C$6)^(D30-1))-$C$7,0,$C$4*D45*(1-2/$C$6)^(D30-1)-$C$7))))) -> 750000 | E76: =IF($C$8=1,(($C$4-$C$7)/$C$6)*E45,(IF($C$7<$C$4*(1-2/$C$6)^(E30),$C$4*(1-2/$C$6)^(E30-1)*(2/$C$6)*E45,(IF(0>($C$4*(1-2/$C$6)^(E30-1))-$C$7,0,$C$4*E45*(1-2/$C$6)^(E30-1)-$C$7))))) -> 750000 | F76: =IF($C$8=1,(($C$4-$C$7)/$C$6)*F45,(IF($C$7<$C$4*(1-2/$C$6)^(F30),$C$4*(1-2/$C$6)^(F30-1)*(2/$C$6)*F45,(IF(0>($C$4*(1-2/$C$6)^(F30-1))-$C$7,0,$C$4*F45*(1-2/$C$6)^(F30-1)-$C$7))))) -> 750000 | G76: =IF($C$8=1,(($C$4-$C$7)/$C$6)*G45,(IF($C$7<$C$4*(1-2/$C$6)^(G30),$C$4*(1-2/$C$6)^(G30-1)*(2/$C$6)*G45,(IF(0>($C$4*(1-2/$C$6)^(G30-1))-$C$7,0,$C$4*G45*(1-2/$C$6)^(G30-1)-$C$7))))) -> 750000 | H76: =IF($C$8=1,(($C$4-$C$7)/$C$6)*H45,(IF($C$7<$C$4*(1-2/$C$6)^(H30),$C$4*(1-2/$C$6)^(H30-1)*(2/$C$6)*H45,(IF(0>($C$4*(1-2/$C$6)^(H30-1))-$C$7,0,$C$4*H45*(1-2/$C$6)^(H30-1)-$C$7))))) -> 750000 | I76: =IF($C$8=1,(($C$4-$C$7)/$C$6)*I45,(IF($C$7<$C$4*(1-2/$C$6)^(I30),$C$4*(1-2/$C$6)^(I30-1)*(2/$C$6)*I45,(IF(0>($C$4*(1-2/$C$6)^(I30-1))-$C$7,0,$C$4*I45*(1-2/$C$6)^(I30-1)-$C$7))))) -> 750000 | J76: =IF($C$8=1,(($C$4-$C$7)/$C$6)*J45,(IF($C$7<$C$4*(1-2/$C$6)^(J30),$C$4*(1-2/$C$6)^(J30-1)*(2/$C$6)*J45,(IF(0>($C$4*(1-2/$C$6)^(J30-1))-$C$7,0,$C$4*J45*(1-2/$C$6)^(J30-1)-$C$7))))) -> 750000 | ... V76: =IF($C$8=1,(($C$4-$C$7)/$C$6)*V45,(IF($C$7<$C$4*(1-2/$C$6)^(V30),$C$4*(1-2/$C$6)^(V30-1)*(2/$C$6)*V45,(IF(0>($C$4*(1-2/$C$6)^(V30-1))-$C$7,0,$C$4*V45*(1-2/$C$6)^(V30-1)-$C$7))))) -> 0
A77: BV(ending) | B77: =C4 -> 11250000 | C77: =C75-C76 -> 10500000 | D77: =D75-D76 -> 9750000 | E77: =E75-E76 -> 9000000 | F77: =F75-F76 -> 8250000 | G77: =G75-G76 -> 7500000 | H77: =H75-H76 -> 6750000 | I77: =I75-I76 -> 6000000 | J77: =J75-J76 -> 5250000 | ... V77: =V75-V76 -> 0

Sheet M2
A1: Unprocessed Feed | Q1: Model Parameters | V1: Revenue Assumptions
A2: Annual Quantity | B2: =#REF!*#REF!*#REF!/1000 -> #REF! | C2: MT/yr | D2: Ratability (Days/ Year) | E2: =Z18 -> 320 | G2: Feed Composition (wt % wb) | J2: Non - Combustible | Q2: Parameter | R2: Value | S2: Units | T2: Comments | V2: Stream | W2: Value | X2: Units | Y2: Comments
A3: Maximum Rate | B3: =B5*E3 -> #REF! | C3: MT/hr | D3: Maximum (% of Typical) | E3: 1.15 | G3: Moisture | H3: Volatile Matter | I3: Fixed Carbon | J3: Ash | K3: Ferrous Metals | L3: Aluminium | N3: LHV (kJ/kg) DAF | O3: NCV (kJ/kg) AR | Q3: Enthalpy Change h2O Drier | R3: 2573 | S3: kJ/kg | T3: 25 to 100 deg C steam | V3: Thermal Value | W3: 10 | X3: AUD/GJ
A4: Minimum Rate | B4: =B5*E4 -> #REF! | C4: MT/hr | D4: Minimum (% of Typical) | E4: 0.85 | G4: =#REF! -> #REF! | H4: =#REF! -> #REF! | I4: =#REF! -> #REF! | J4: =#REF! -> #REF! | K4: =#REF! -> #REF! | L4: =#REF! -> #REF! | N4: =#REF! -> #REF! | O4: =(((N4/1000)*(1-(J4*(1/(1-G4)))/1)*((1-G4)/1))-(0.02443*G4))*1000 -> #REF! | Q4: Specific Heat Drier Gas | R4: 1.05 | S4: kJ/kg/C | V4: Char Value | W4: 0.2 | X4: AUD/kg
A5: Typical Rate | B5: =B2/E2/24 -> #REF! | C5: MT/hr | D5: Natural Ratability (Days/year) | E5: 320 | I5: Total | J5: =SUM(J4:L4) -> #REF! | Q5: Enthalpy Change feed | R5: =1.3*(G66-25) -> 552.5 | S5: kJ/kg | T5: Linked to Reactor Temp | V5: Waste Disposal Fee/ (cost) | W5: -0.05 | X5: AUD/kg
A6: Storage | B6: =(E2-E5)*24*B5*1000/R12 -> #REF! | C6: m3 | G6: =G4*$B$5*1000 -> #REF! | H6: =H4*$B$5*1000 -> #REF! | I6: =I4*$B$5*1000 -> #REF! | J6: =J4*$B$5*1000 -> #REF! | K6: =K4*$B$5*1000 -> #REF! | L6: =L4*$B$5*1000 -> #REF! | N6: =B5*1000-G6-J6 -> #REF! | Q6: Enthalpy Change h2O Gasifier | R6: =4050-(1.5*(1200-H66)) -> 3525 | S6: kJ/kg | T6: Linked to Ox Temp | V6: Electricity Value | W6: 0.15 | X6: AUD/kWh
Q7: Air Required | R7: =(1/12)/0.21*29*R10 -> 13.809524 | S7: kg/kg | T7: of fuel burnt | V7: Water Value | W7: 0.001 | X7: AUD/kg
A8: Supplemental Feed | Q8: Enthalpy Change Air | R8: =1*(H66-25) -> 825 | S8: kJ/kg | T8: Linked to Ox Temp | V8: Supp Feed Value/ (Cost) | W8: 0 | X8: AUD/kg
A9: Annual Quantity | B9: 0 | C9: MT/yr | D9: Ratability (Days/ Year) | E9: =Z18 -> 320 | G9: Feed Composition (wt % wb) | J9: Non - Combustible | Q9: Heat Loss | R9: 0.03 | S9: % | T9: % of Qfuel | V9: GHG Credit Value | W9: 0.2 | X9: AUD/kg
A10: Maximum Rate | B10: =B12*E10 -> 0 | C10: MT/hr | D10: Maximum (% of Typical) | E10: 1.15 | G10: Moisture | H10: Volatile Matter | I10: Fixed Carbon | J10: Ash | K10: Ferrous Metals | L10: Aluminium | N10: LHV (kJ/kg) DAF | O10: NCV (kJ/kg) AR | Q10: XS Air | R10: =I66 -> 1.2 | S10: % | T10: Linked to Gasification Unit | V10: Dewatered Product Value | W10: 0 | X10: AUD/kg
A11: Minimum Rate | B11: =B12*E11 -> 0 | C11: MT/hr | D11: Minimum (% of Typical) | E11: 0.85 | G11: 0.1 | H11: =(1-G11)*0.8 -> 0.72 | I11: =(1-G11)*0.193 -> 0.1737 | J11: =(1-G11)*0.7% -> 0.0063 | K11: 0 | L11: 0 | N11: 18800 | O11: =(((N11/1000)*(1-(J11*(1/(1-G11)))/1)*((1-G11)/1))-(0.02443*G11))*1000 -> 16799.117 | Q11: Dryer Efficiency | R11: 3300 | S11: kJ/kg | T11: of water removal | V11: Dried Product Value | W11: 0.1 | X11: AUD/kg
A12: Typical Rate | B12: =B9/E9/24 -> 0 | C12: MT/hr | D12: Natural Ratability (Days/year) | E12: 120 | I12: Total | J12: =SUM(J11:L11) -> 0.0063 | Q12: Bulk Density Feed | R12: 700 | S12: kg/m3 | V12: Weighted Feed Value/ (Cost) | W12: =(B2*W5+B9*W8)/(B2+B9) -> #REF! | X12: AUD/kg
A13: Storage | B13: =(E9-E12)*24*B12*1000/R12 -> 0 | C13: m3 | G13: =G11*$B$12*1000 -> 0 | H13: =H11*$B$12*1000 -> 0 | I13: =I11*$B$12*1000 -> 0 | J13: =J11*$B$12*1000 -> 0 | K13: =K11*$B$12*1000 -> 0 | L13: =L11*$B$12*1000 -> 0 | N13: =B12*1000-G13-J13 -> 0 | V13: Metal Value | W13: 1 | X13: AUD/kg
Q14: Cost Assumptions
A15: Blended Feed | Q15: Parameter | R15: Value | S15: Units | T15: Comments | V15: O&M Summary | Y15: O&M Assumptions
A16: Annual Quantity | B16: =B2+B9 -> #REF! | C16: MT/yr | D16: Ratability (Days/ Year) | E16: =Z18 -> 320 | G16: Feed Composition (wt % wb) | J16: Non - Combustible | Q16: Storage Cost | R16: 50 | S16: $/m3 | V16: Mgmt OvHd | W16: =Z28*W17 -> 45000 | Y16: Parameter | Z16: Value | AA16: Units | AB16: Comments
A17: Maximum Rate | B17: =B3+B10 -> #REF! | C17: MT/hr | D17: Maximum (% of Typical) | E17: =B17/B19 -> #REF! | G17: Moisture | H17: Volatile Matter | I17: Fixed Carbon | J17: Ash | K17: Ferrous Metals | L17: Aluminium | N17: LHV (kJ/kg) DAF | O17: NCV (kJ/kg) AR | Q17: TIC Electrical Gen | R17: 3750 | S17: AUD/kW | V17: Direct SWB | W17: =Z25*Z26 -> 450000 | Y17: Hrs/ Day | Z17: 24
A18: Minimum Rate | B18: =B4+B11 -> #REF! | C18: MT/hr | D18: Minimum (% of Typical) | E18: =B18/B19 -> #REF! | G18: =G20/SUM($G$20:$L$20) -> #REF! | H18: =H20/SUM($G$20:$L$20) -> #REF! | I18: =I20/SUM($G$20:$L$20) -> #REF! | J18: =J20/SUM($G$20:$L$20) -> #REF! | K18: =K20/SUM($G$20:$L$20) -> #REF! | L18: =L20/SUM($G$20:$L$20) -> #REF! | N18: =(N4*N6+N11*N13)/(N6+N13) -> #REF! | O18: =(((N18/1000)*(1-(J18*(1/(1-G18)))/1)*((1-G18)/1))-(0.02443*G18))*1000 -> #REF! | Q18: Exchange Rate | R18: 1.5 | S18: USD/AUD | Y18: Days/ Year | Z18: 320
A19: Typical Rate | B19: =B5+B12 -> #REF! | C19: MT/hr | D19: Natural Ratability (Days/year) | E19: 320 | I19: Total | J19: =SUM(J18:L18) -> #REF! | Q19: Interest Rate | R19: 0.08 | S19: % | V19: Energy Costs | W19: =Z30*W6*Z17*Z18 -> #REF! | Y19: Number of Ops positions | Z19: 1
A20: Storage | B20: =(E16-E19)*24*B19*1000/R12 -> #REF! | C20: m3 | G20: =G6+G13 -> #REF! | H20: =H6+H13 -> #REF! | I20: =I6+I13 -> #REF! | J20: =J6+J13 -> #REF! | K20: =K6+K13 -> #REF! | L20: =L6+L13 -> #REF! | N20: =N6+N13 -> #REF! | Q20: Loan Length | R20: 10 | S20: years | V20: Other | W20: =Z17*Z18*Z31 -> 76800 | Y20: hrs per Shift | Z20: 12
Q21: Leverage | R21: 2 | Y21: shifts per week | Z21: =24*7/Z20 -> 14
Q22: CAPEX Discount | R22: 0 | S22: % | V22: Direct Maintenance | W22: =Z33*(B90-B88) -> #REF! | Y22: working hours a week | Z22: 40
A23: Dewater | E23: Dewatered Product | Q23: Water Treatment Cost | R23: 0.1 | S23: AUD/m3 | V23: Accrued Maintenance | W23: =Z34*(B90-B88) -> #REF! | Y23: maximum shifts per person | Z23: =ROUND(Z22/Z20,0) -> 3
A24: Feed to Dewatering | B24: 0 | C24: % of Blended | E24: Rate | F24: =B27+B30 -> #REF! | G24: kg/hr | H24: Sold | I24: =F24*F25 -> #REF! | J24: kg/hr | Y24: Required Number of shift groups | Z24: =ROUND(Z21/Z23,0) -> 5
A25: %DS | B25: 0.3 | C25: % | E25: Sale Fraction | F25: 0 | G25: % | H25: NCV AR | I25: =(((N18/1000)*(1-(H29*(1/(1-E29)))/1)*((1-E29)/1))-(0.02443*E29))*1000 -> #REF! | J25: kJ/kg | Y25: number of Operators | Z25: =Z24*Z19 -> 5
A26: Total Feed | B26: =B24*B19*1000 -> #REF! | C26: kg/hr | Q26: Gasification Cost Assumptions | Y26: Average Salary | Z26: 90000
A27: Solids | B27: =(1-G18)*B26 -> #REF! | C27: kg/hr | E27: Feed Composition (wt % wb) | H27: Non - Combustible | Q27: Feed Rate (kg/hr) | R27: Gassification Costs (KUSD) | S27: TIC Factor | T27: TIC KUSD | U27: TIC KAUD | V27: Maximum GJ/hr
A28: Water In | B28: =B26-B27 -> #REF! | C28: kg/hr | E28: Moisture | F28: Volatile Matter | G28: Fixed Carbon | H28: Ash | I28: Ferrous Metals | J28: Aluminium | Q28: 300 | R28: =850 -> 850 | S28: 2 | T28: =R28*S28 -> 1700 | U28: =T28*$R$18 -> 2550 | V28: 3.4 | Y28: Mgmt OvHd | Z28: 0.1 | AA28: % of SWB
A29: Water Removed | B29: =B28-B30 -> #REF! | C29: kg/hr | E29: =(G20-B29)/(G20-B29+H20+I20+J20+K20+L20) -> #REF! | F29: =H20/(G20-B29+H20+I20+J20+K20+L20) -> #REF! | G29: =I20/(G20-B29+H20+I20+J20+K20+L20) -> #REF! | H29: =J20/(G20-B29+H20+I20+J20+K20+L20) -> #REF! | I29: =K20/(G20-B29+H20+I20+J20+K20+L20) -> #REF! | J29: =L20/(G20-B29+H20+I20+J20+K20+L20) -> #REF! | Q29: 600 | R29: =2*850 -> 1700 | S29: 1.5 | T29: =R29*S29 -> 2550 | U29: =T29*$R$18 -> 3825 | V29: =2*V28 -> 6.8
A30: Water Remaining | B30: =B27/B25-B27 -> #REF! | C30: kg/hr | G30: Total Ash | H30: =SUM(H29:J29) -> #REF! | Q30: 900 | R30: =3*850 -> 2550 | S30: 1.5 | T30: =R30*S30 -> 3825 | U30: =T30*$R$18 -> 5737.5 | V30: 15 | Y30: Energy Requirement | Z30: =50+75*E63/1000+175*B36/5000 -> #REF! | AA30: kW
Q31: 1000 | R31: =2500 -> 2500 | S31: 2 | T31: =R31*S31 -> 5000 | U31: =T31*$R$18 -> 7500 | V31: 15 | Y31: Other | Z31: 10 | AA31: AUD/hr
A32: Dryer | Q32: 1300 | R32: =(850+2500) -> 3350 | S32: 1.5 | T32: =R32*S32 -> 5025 | U32: =T32*$R$18 -> 7537.5 | V32: =V31+V28 -> 18.4
A33: Feed to Dryer | B33: 0 | C33: % of DeW or Blended | E33: Dried Product | M33: Thermal | Q33: 1600 | R33: =(850*2+2500) -> 4200 | S33: 1.5 | T33: =R33*S33 -> 6300 | U33: =T33*$R$18 -> 9450 | V33: =V31+V29 -> 21.8 | Y33: Direct Maintenance | Z33: 0.03 | AA33: % of TIC
A34: Feed to Dryer | B34: =IF(F24>0,B33*F24,B33*B19*1000) -> #REF! | C34: kg/hr | E34: Rate | F34: =B34-B37 -> #REF! | G34: kg/hr | H34: Sold | I34: =F34*F35 -> #REF! | J34: kg/hr | M34: Condensing Service | N34: 0 | O34: Yes/No | Q34: 1900 | R34: =2*2500 -> 5000 | S34: 1.5 | T34: =R34*S34 -> 7500 | U34: =T34*$R$18 -> 11250 | V34: =2*V31 -> 30 | Y34: Accrued Maintenance | Z34: 0.03 | AA34: % of TIC
A35: Water Removal | B35: 0.9 | C35: % | E35: Sale Fraction | F35: 0 | G35: % | H35: NCV AR | I35: =(((N18/1000)*(1-(H39*(1/(1-E39)))/1)*((1-E39)/1))-(0.02443*E39))*1000 -> #REF! | J35: kJ/kg | M35: Recovery | N35: 0.85 | O35: % | Q35: 2000 | R35: =2*2500 -> 5000 | S35: 1.5 | T35: =R35*S35 -> 7500 | U35: =T35*$R$18 -> 11250 | V35: =2*V31 -> 30
A36: Water In | B36: =E29*B34 -> #REF! | C36: kg/hr | M36: Outlet Temp | N36: 120 | O36: deg C | Q36: 2300 | R36: =2*2500+850 -> 5850 | S36: 1.5 | T36: =R36*S36 -> 8775 | U36: =T36*$R$18 -> 13162.5 | V36: =V35+V28 -> 33.4
A37: Water Removed | B37: =B35*B36 -> #REF! | C37: kg/hr | E37: Feed Composition (wt % wb) | H37: Non - Combustible | M37: Specific Heat | N37: 1 | O37: kJ/kg/C | Q37: 2600 | R37: =2*2500+2*850 -> 6700 | S37: 1.5 | T37: =R37*S37 -> 10050 | U37: =T37*$R$18 -> 15075 | V37: =V35+V29 -> 36.8
A38: Water Remaining | B38: =B36-B37 -> #REF! | C38: kg/hr | E38: Moisture | F38: Volatile Matter | G38: Fixed Carbon | H38: Ash | I38: Ferrous Metals | J38: Aluminium | M38: Valuable Energy | N38: =IFERROR(((850-N36)*(E63-E66-E68+F66)*N37+(2260*F68*N34))/1000/1000*N35*(1-MAX(B49,B48)),0) -> 0 | O38: GJ/hr | Q38: 2900 | R38: =3*2500 -> 7500 | S38: 1.5 | T38: =R38*S38 -> 11250 | U38: =T38*$R$18 -> 16875 | V38: 45 | Y38: CAPEX Assumptions
A39: Energy Requirement | B39: =B37*R11/1000/1000 -> #REF! | C39: GJ/hr | E39: =IFERROR(B38/F34,0) -> 0 | F39: =IFERROR(B33*H20/F34,0) -> 0 | G39: =IFERROR(B33*I20/F34,0) -> 0 | H39: =IFERROR(B33*J20/F34,0) -> 0 | I39: =IFERROR(B33*K18/F34,0) -> 0 | J39: =IFERROR(B33*L18/F34,0) -> 0 | M39: Check | N39: =N35*B51 -> #REF! | O39: GJ/hr | Q39: 3000 | R39: =3*2500 -> 7500 | S39: 1.5 | T39: =R39*S39 -> 11250 | U39: =T39*$R$18 -> 16875 | V39: 45 | Z39: CAPEX (AUD)
A40: Gasification Flue | B40: =((B44-B43)/(H66-B43))*B42 -> #REF! | C40: kg/hr | G40: Total Ash | H40: =SUM(H39:J39) -> 0 | Q40: 3300 | R40: =3*2500+850 -> 8350 | S40: 1.5 | T40: =R40*S40 -> 12525 | U40: =T40*$R$18 -> 18787.5 | V40: =V39+V28 -> 48.4 | Y40: Material Handling | Z40: 0
A41: Recycled Flue | B41: =(1-((B44-B46)/(H66-B46)))*B42 -> #REF! | C41: kg/hr | M41: Electricity Gen | Q41: 3600 | R41: =3*2500+2*850 -> 9200 | S41: 1.5 | T41: =R41*S41 -> 13800 | U41: =T41*$R$18 -> 20700 | V41: =V39+V29 -> 51.8 | Y41: Dewater | Z41: =U62*1000 -> #REF!
A42: Total Drier Flow | B42: =B47 -> #REF! | C42: kg/hr | E42: Straight Feed | M42: Service | N42: 0 | O42: Yes/ No | Q42: 3900 | R42: =4*2500 -> 10000 | S42: 1.5 | T42: =R42*S42 -> 15000 | U42: =T42*$R$18 -> 22500 | V42: =4*15 -> 60 | Y42: Dryer | Z42: {=IF(AND(B33>0,B35>0),IFERROR(INDEX(Q48:U57,MATCH(B37,Q48:Q57,1)+1,5)*1000,U48*1000),0)} -> 0
A43: Recycle Temp | B43: 120 | C43: deg C | E43: Rate | F43: =B19*1000-MAX(B26,B34) -> #REF! | G43: kg/hr | H43: Sold | I43: =F43*F44 -> #REF! | J43: kg/hr | M43: Efficiency | N43: 0.3 | O43: % | Q43: 4000 | R43: =4*2500 -> 10000 | S43: 1.5 | T43: =R43*S43 -> 15000 | U43: =T43*$R$18 -> 22500 | V43: 60 | Y43: Gasification | Z43: {=IF(E63=0,0,IFERROR(INDEX(Q28:U43,MATCH(E63,Q28:Q43,1)+1,5)*1000,U28*1000))} -> #REF!
A44: Inlet Temp | B44: 530 | C44: deg C | E44: Sale Fraction | F44: 0 | H44: NCV AR | I44: =(((N18/1000)*(1-(H48*(1/(1-E48)))/1)*((1-E48)/1))-(0.02443*E48))*1000 -> #REF! | J44: kJ/kg | M44: KW | N44: =N38*N43*N42*1000*1000/3600 -> 0 | Y44: Electricity Gen | Z44: =N44*R17 -> 0
Y45: Storage | Z45: =B6*R16+B13*R16+B20*R16 -> #REF!
A46: Minimum Outlet Temp | B46: 120 | C46: deg C | E46: Feed Composition (wt % wb) | H46: Non - Combustible | Q46: Drier Cost Assumptions | Y46: Balance of Plant | Z46: 0
A47: Minimum Flow Rate | B47: =(B39*1000*1000)/((B44-B46)*R4) -> #REF! | C47: kg/hr | E47: Moisture | F47: Volatile Matter | G47: Fixed Carbon | H47: Ash | I47: Ferrous Metals | J47: Aluminium | M47: Resource Recovery | Q47: Water Removal (kg/hr) | R47: Drier Costs (KUSD) | S47: TIC Factor | T47: TIC KUSD | U47: TIC KAUD | Y47: Ash/ Char Recovery | Z47: 0
A48: Fraction of Flue Q | B48: =B39/(I63+J63) -> #REF! | C48: % | E48: =G18 -> #REF! | F48: =H18 -> #REF! | G48: =I18 -> #REF! | H48: =J18 -> #REF! | I48: =K18 -> #REF! | J48: =L18 -> #REF! | M48: Service | N48: 0 | O48: Yes/ No | Q48: 1000 | R48: =950 -> 950 | S48: 1.1 | T48: =R48*S48 -> 1045 | U48: =T48*$R$18 -> 1567.5 | Y48: Electrical | Z48: 0
A49: Fraction of Flue Flow | B49: =B40/(E63-E66-E68+F66) -> #REF! | C49: % | G49: Total Ash | H49: =SUM(H48:J48) -> #REF! | M49: Recovery | N49: 1 | O49: % | Q49: 2000 | R49: =2*950 -> 1900 | S49: 1.1 | T49: =R49*S49 -> 2090 | U49: =T49*$R$18 -> 3135 | Y49: Civil | Z49: 0
A50: Actual Outlet Temp | B50: =B44-(B39*1000*1000/((R4*B42))) -> #REF! | C50: deg C | M50: CAPEX | N50: 1000000 | O50: AUD | Q50: 3000 | R50: 2750 | S50: 1.1 | T50: =R50*S50 -> 3025 | U50: =T50*$R$18 -> 4537.5 | Y50: Site and Buildings | Z50: 0
A51: Qt | B51: =I63+J63-B39 -> #REF! | C51: GJ/hr | Q51: 4000 | R51: 2750 | S51: 1.1 | T51: =R51*S51 -> 3025 | U51: =T51*$R$18 -> 4537.5 | Y51: Discount | Z51: =-R22*(Z42+Z43) -> #REF!
E52: Gasifier | Q52: 5000 | R52: 2750 | S52: 1.1 | T52: =R52*S52 -> 3025 | U52: =T52*$R$18 -> 4537.5
M53: Flue | Q53: 6000 | R53: =2750+950 -> 3700 | S53: 1.1 | T53: =R53*S53 -> 4070 | U53: =T53*$R$18 -> 6105
M54: Water Useable | N54: 1 | O54: Yes/No | Q54: 7000 | R54: =2750+2*950 -> 4650 | S54: 1.1 | T54: =R54*S54 -> 5115 | U54: =T54*$R$18 -> 7672.5
E55: Feed Composition (wt % wb) | H55: Non - Combustible | M55: Water Recovered | N55: =B37+E57*E63 -> #REF! | O55: kg/hr | Q55: 8000 | R55: =2*2750 -> 5500 | S55: 1.1 | T55: =R55*S55 -> 6050 | U55: =T55*$R$18 -> 9075
E56: Moisture | F56: Volatile Matter | G56: Fixed Carbon | H56: Ash | I56: Ferrous Metals | J56: Aluminium | M56: GHG Credits | N56: 1.5 | O56: kg/kg of feed wb | Q56: 9000 | R56: =2*2750 -> 5500 | S56: 1.1 | T56: =R56*S56 -> 6050 | U56: =T56*$R$18 -> 9075
E57: =IFERROR(((F34-I34)*E39+(F43*E48)+((F24-I24)*E29))/(F34-I34+F43+F24-I24),0) -> 0 | F57: =IFERROR(((F34-I34)*F39+(F43*F48)+((F24-I24)*F29))/(F34-I34+F43+F24-I24),0) -> 0 | G57: =IFERROR(((F34-I34)*G39+(F43*G48)+((F24-I24)*G29))/(F34-I34+F43+F24-I24),0) -> 0 | H57: =IFERROR(((F34-I34)*H39+(F43*H48)+((F24-I24)*H29))/(F34-I34+F43+F24-I24),0) -> 0 | I57: =IFERROR(((F34-I34)*I39+(F43*I48)+((F24-I24)*I29))/(F34-I34+F43+F24-I24),0) -> 0 | J57: =IFERROR(((F34-I34)*J39+(F43*J48)+((F24-I24)*J29))/(F34-I34+F43+F24-I24),0) -> 0 | M57: GHG Credits | N57: 2.2 | O57: kg/kg of Char | Q57: 10000 | R57: =2*2750 -> 5500 | S57: 1.1 | T57: =R57*S57 -> 6050 | U57: =T57*$R$18 -> 9075
G58: Total Ash | H58: =SUM(H57:J57) -> 0 | M58: GHG Credits | N58: =IF(N57="",B5*Z17*Z18*N56,N57*E66*Z17*Z18/1000) -> #REF! | O58: MT/yr
H59: NCV AR | I59: =(((N18/1000)*(1-(H57*(1/(1-E57)))/1)*((1-E57)/1))-(0.02443*E57))*1000 -> #REF! | J59: kJ/kg
Q60: Dewatering Cost Assumptions
G61: QIn | H61: QOut | Q61: Dewatering Costs (KUSD/kg/hr f) | R61: Dewater Costs (KUSD) | S61: TIC Factor | T61: TIC KUSD | U61: TIC KAUD
E62: Rate kg/hr | F62: DAF kg/hr | G62: Qfuel (GJ/hr) | H62: Qfeed (GJ/hr) | I62: Qh2O (GJ/hr) | J62: Qair (GJ/hr) | K62: Qloss (GJ/hr) | L62: Balance (GJ/hr) | Q62: 0.05 | R62: =B26*Q62 -> #REF! | S62: 1.1 | T62: =R62*S62 -> #REF! | U62: =T62*$R$18 -> #REF!
E63: =F34-I34+F43-I43+F24-I24 -> #REF! | F63: =E63*(1-E57-H58) -> #REF! | G63: =F63*N18/1000/1000 -> #REF! | H63: =(E63-F68)*R5/1000/1000 -> #REF! | I63: =$R$6*E57*E63/1000/1000 -> #REF! | J63: =($R$8*(($R$7*(F63))/1000/1000)) -> #REF! | K63: =G63*R9 -> #REF! | L63: =G63-SUM(H63:K63) -> #REF!
F64: Max GJ/hr | G64: {=IFERROR(INDEX(Q28:V43,MATCH(E63,Q28:Q43,1)+1,6),V28)} -> 3.4 | H64: =SUM(I63:K63) -> #REF!
E65: Unburnt Fuel (kg/hr) | F65: Air (kg/hr) | G65: Reactor Temp | H65: Oxidizer Temp | I65: XS Air
E66: =L63*1000*1000/N18 -> #REF! | F66: =R7*F63 -> #REF! | G66: 450 | H66: 850 | I66: 1.2
E67: Ash (kg/hr) | F67: Water (kg/hr) | I67: =F66/((F63-E66)*(1/12)/0.21*29) -> #REF!
E68: =H58*E63 -> #REF! | F68: =E57*E63 -> #REF!
E69: Char % | F69: =E66/E63 -> #REF!
D73: Income Statement
D74: Waste Disposal | E74: =IF(W5>0,B2*1000*W5,0)+IF(W8>0,B9*1000*W8,0) -> 0
D75: Product Sale | E75: =(I34*W11+I24*W10-I43*W12)*Z17*Z18 -> #REF!
B76: CAPEX (AUD) | D76: Char | E76: =(E66+E68)*W4*Z17*Z18 -> #REF!
A77: Material Handling | B77: =Z40 -> 0 | D77: Thermal Energy | E77: =IF(N42=0,N38*Z17*Z18*W3,0) -> 0 | G77: NPV (AUD) | H77: ='NPV2'!C54 -> #REF!
A78: Dewater | B78: =Z41 -> #REF! | D78: Electricity Gen | E78: =Z17*Z18*N44*W6 -> 0
A79: Dryer | B79: =Z42 -> 0 | D79: Water | E79: =IF(N54=1,Z17*Z18*N55*W7,0) -> #REF! | G79: ROE | H79: =E98/(B90/R21) -> #REF!
A80: Gasification | B80: =Z43 -> #REF! | D80: Resource Recovery | E80: =SUM(K18:L18)*B19*1000*Z17*Z18*N49*N48*W13 -> #REF!
A81: Electricity Gen | B81: =Z44 -> 0 | D81: GHG Credits | E81: =N58*1000*W9 -> #REF! | G81: ROA | H81: =E100/B90 -> #REF! | J81: Interest Efficiency | K81: =E98/E100 -> #REF!
A82: Storage | B82: =Z45 -> #REF! | G82: Asset Turnover | H82: =E83/B90 -> #REF! | J82: Leverage | K82: =R21 -> 2
A83: Balance of Plant | B83: =Z46 -> 0 | D83: Total Revenue | E83: =SUM(E74:E81) -> #REF! | G83: Operating Efficiency | H83: =E100/E83 -> #REF!
A84: Resource Recovery | B84: =Z47 -> 0
A85: Electrical | B85: =Z48 -> 0 | D85: Feed Cost | E85: =IF(W5>0,0,-B2*1000*W5)+IF(W8>0,0,-B9*1000*W8) -> #REF!
A86: Civil | B86: =Z49 -> 0 | D86: O&M Variable | E86: =W19+W20+W22+IF(N54=0,N55*Z17*Z18*R23) -> #REF! | I86: Subsidised with Revenues
A87: Site and Buildings | B87: =Z50 -> 0 | D87: O&M Fixed | E87: =W16+W17+W23 -> #REF! | H87: Full Cost | I87: Waste Disposal | J87: Product Sale | K87: Char | L87: Water | M87: Resource Recovery | N87: GHG Credits | O87: Full Subsidy
A88: Discount | B88: =Z51 -> #REF! | D88: Operating Expenses | E88: =SUM(E85:E87) -> #REF! | G88: Revenue | H88: 0 | I88: =IFERROR(INDEX(Revenue,MATCH(I87,Rev_Stream,0),2),0) -> 0 | J88: =IFERROR(INDEX(Revenue,MATCH(J87,Rev_Stream,0),2),0) -> 0 | K88: =IFERROR(INDEX(Revenue,MATCH(K87,Rev_Stream,0),2),0) -> 0 | L88: =IFERROR(INDEX(Revenue,MATCH(L87,Rev_Stream,0),2),0) -> 0 | M88: =IFERROR(INDEX(Revenue,MATCH(M87,Rev_Stream,0),2),0) -> 0 | N88: =IFERROR(INDEX(Revenue,MATCH(N87,Rev_Stream,0),2),0) -> 0 | O88: =SUM(I88:N88) -> 0
G89: OPEX | H89: =E88 -> #REF! | I89: =H89 -> #REF! | J89: =I89 -> #REF! | K89: =J89 -> #REF! | L89: =K89 -> #REF! | M89: =L89 -> #REF! | N89: =M89 -> #REF! | O89: =N89 -> #REF!
A90: Total Installed CAPEX | B90: =SUM(B78:B88) -> #REF! | D90: Operating Profit/ (Loss) | E90: =E83-E88 -> #REF! | G90: CAPEX | H90: =PMT(#REF!,#REF!,-'M2'!B90+B81) -> #REF! | I90: =H90 -> #REF! | J90: =I90 -> #REF! | K90: =J90 -> #REF! | L90: =K90 -> #REF! | M90: =L90 -> #REF! | N90: =M90 -> #REF! | O90: =N90 -> #REF!
G91: Total | H91: =SUM(H89:H90) -> #REF! | I91: =SUM(I89:I90)-I88 -> #REF! | J91: =SUM(J89:J90)-J88 -> #REF! | K91: =SUM(K89:K90)-K88 -> #REF! | L91: =SUM(L89:L90)-L88 -> #REF! | M91: =SUM(M89:M90)-M88 -> #REF! | N91: =SUM(N89:N90)-N88 -> #REF! | O91: =SUM(O89:O90)-O88 -> #REF!
D92: Interest | E92: =IPMT(R19,1,R20,-(B90-B90/R21)) -> #REF!
G93: Total Energy (GJ/yr) | H93: =Z17*Z18*H64 -> #REF! | I93: =H93 -> #REF! | J93: =I93 -> #REF! | K93: =J93 -> #REF! | L93: =K93 -> #REF! | M93: =L93 -> #REF! | N93: =M93 -> #REF! | O93: =N93 -> #REF!
D94: Income before Taxes | E94: =E90-E92 -> #REF! | G94: Net Drying (GJ/yr) | H94: =B51*Z17*Z18 -> #REF! | I94: =H94 -> #REF! | J94: =I94 -> #REF! | K94: =J94 -> #REF! | L94: =K94 -> #REF! | M94: =L94 -> #REF! | N94: =M94 -> #REF! | O94: =N94 -> #REF!
D96: Taxes | E96: =E94*0.3 -> #REF! | G96: Energy Cost (AUD/GJ) | H96: =H91/H93 -> #REF! | I96: =I91/I93 -> #REF! | J96: =J91/J93 -> #REF! | K96: =K91/K93 -> #REF! | L96: =L91/L93 -> #REF! | M96: =M91/M93 -> #REF! | N96: =N91/N93 -> #REF! | O96: =O91/O93 -> #REF!
G97: Energy Cost Net Drying (AUD/GJ) | H97: =H91/H94 -> #REF! | I97: =I91/I94 -> #REF! | J97: =J91/J94 -> #REF! | K97: =K91/K94 -> #REF! | L97: =L91/L94 -> #REF! | M97: =M91/M94 -> #REF! | N97: =N91/N94 -> #REF! | O97: =O91/O94 -> #REF!
D98: Net Income | E98: =E94-E96 -> #REF!
G99: Electrical Capability (kW) @ 30% eff | H99: =H94/Z17/Z18*1000*1000/3600*0.3*0.85 -> #REF! | I99: =H99 -> #REF! | J99: =I99 -> #REF! | K99: =J99 -> #REF! | L99: =K99 -> #REF! | M99: =L99 -> #REF! | N99: =M99 -> #REF! | O99: =N99 -> #REF!
D100: NOPAT | E100: =E98+(E92*(1-0.3)) -> #REF! | G100: Electricity Gen (kWh) @ 30% eff | H100: =H94*1000*1000/3600*0.3*0.85 -> #REF! | I100: =H100 -> #REF! | J100: =I100 -> #REF! | K100: =J100 -> #REF! | L100: =K100 -> #REF! | M100: =L100 -> #REF! | N100: =M100 -> #REF! | O100: =N100 -> #REF!
G101: CAPEX | H101: =PMT(#REF!,#REF!,-H99*R17) -> #REF! | I101: =H101 -> #REF! | J101: =I101 -> #REF! | K101: =J101 -> #REF! | L101: =K101 -> #REF! | M101: =L101 -> #REF! | N101: =M101 -> #REF! | O101: =N101 -> #REF!
G102: Total Cost | H102: =H91+H101 -> #REF! | I102: =I91+I101 -> #REF! | J102: =J91+J101 -> #REF! | K102: =K91+K101 -> #REF! | L102: =L91+L101 -> #REF! | M102: =M91+M101 -> #REF! | N102: =N91+N101 -> #REF! | O102: =O91+O101 -> #REF!
G103: Electricity Cost (AUD/kWh) | H103: =H102/H100 -> #REF! | I103: =I102/I100 -> #REF! | J103: =J102/J100 -> #REF! | K103: =K102/K100 -> #REF! | L103: =L102/L100 -> #REF! | M103: =M102/M100 -> #REF! | N103: =N102/N100 -> #REF! | O103: =O102/O100 -> #REF!
G105: Benchmark (AUD/GJ) | H105: 10
...

Sheet NPV2
A1: Equity Analysis of a Project
E2: INPUT SHEET: USER ENTERS ALL BOLD NUMBERS
A3: INITIAL INVESTMENT | E3: CASHFLOW DETAILS | I3: DISCOUNT RATE
A4: Initial Investment= | C4: ='M2'!B90 -> #REF! | E4: Revenues in year 1= | G4: ='M2'!E83 -> #REF! | I4: Approach(1:Direct;2:CAPM)= | K4: 2
A5: Opportunity cost (if any)= | C5: =#REF! -> #REF! | E5: Var. Expenses as % of Rev= | G5: =SUM('M2'!E85:E86)/'M2'!E83 -> #REF! | I5: 1. Discount rate = | K5: 0.08
A6: Lifetime of the investment | C6: 10 | E6: Fixed expenses in year 1= | G6: ='M2'!E87 -> #REF! | I6: 2a. Beta | K6: 1
A7: Salvage Value at end of project= | C7: 0 | E7: Tax rate on net income= | G7: 0.3 | I7: b. Riskless rate= | K7: 0.04
A8: Deprec. method(1:St.line;2:DDB)= | C8: 1 | E8: If you do not have the breakdown of fixed and variable | I8: c. Market risk premium = | K8: 0.08
A9: Tax Credit (if any )= | C9: 0 | E9: expenses, input the entire expense as a % of revenues. | I9: d. Debt Ratio = | K9: =1-1/'M2'!R21 -> 0.5
A10: Other invest.(non-depreciable)= | C10: 0 | I10: e. Cost of Borrowing = | K10: =#REF! -> #REF!
I11: Discount rate used= | K11: =IF(K4=1,K5,(K7+K6*K8)*(1-K9)+K10*(1-G7)*K9) -> #REF!
A12: WORKING CAPITAL
A13: Initial Investment in Work. Cap= | C13: 0
A14: Working Capital as % of Rev= | C14: 0
A15: Salvageable fraction at end= | C15: 1
A17: GROWTH RATES
C18: 1 | D18: 2 | E18: 3 | F18: 4 | G18: 5 | H18: 6 | I18: 7 | J18: 8 | K18: 9 | L18: 10 | M18: 11 | N18: 12 | O18: 13 | P18: 14 | Q18: 15 | R18: 16 | S18: 17 | T18: 18 | U18: 19 | V18: 20
A19: Revenues | C19: Do not enter | D19: 0.03 | E19: 0.03 | F19: 0.03 | G19: 0.03 | H19: 0.03 | I19: 0.03 | J19: 0.03 | K19: 0.03 | L19: 0.03 | M19: 0.03 | N19: 0.03 | O19: 0.03 | P19: 0.03 | Q19: 0.03 | R19: 0.03 | S19: 0.03 | T19: 0.03 | U19: 0.03 | V19: 0.03
A20: Fixed Expenses | C20: Do not enter | D20: =D19 -> 0.03 | E20: =E19 -> 0.03 | F20: =F19 -> 0.03 | G20: =G19 -> 0.03 | H20: =H19 -> 0.03 | I20: =I19 -> 0.03 | J20: =J19 -> 0.03 | K20: =K19 -> 0.03 | ... V20: =V19 -> 0.03
A21: Default: The fixed expense growth rate is set equal to the growth rate in revenues by default.
F22: YEAR
B23: 0 | C23: 1 | D23: 2 | E23: 3 | F23: 4 | G23: 5 | H23: 6 | I23: 7 | J23: 8 | K23: 9 | L23: 10 | M23: 11 | N23: 12 | O23: 13 | P23: 14 | Q23: 15 | R23: 16 | S23: 17 | T23: 18 | U23: 19 | V23: 20
A24: INVESTMENTS
A25: Investment | B25: =C4 -> #REF!
A26: - Tax Credit | B26: =C4*C9 -> #REF!
A27: Net Investment | B27: =B25-B26 -> #REF!
A28: + Working Cap | B28: =C13 -> 0
A29: + Opp. Cost | B29: =C5 -> #REF!
A30: + Other invest. | B30: =C10 -> 0
A31: Investments | B31: =B27+B28+B29+B30 -> #REF!
A33: SALVAGE VALUE
A34: Equipment | C34: =IF(C23=$C$6,$C$7,0) -> 0 | D34: =IF(D23=$C$6,$C$7,0) -> 0 | E34: =IF(E23=$C$6,$C$7,0) -> 0 | F34: =IF(F23=$C$6,$C$7,0) -> 0 | G34: =IF(G23=$C$6,$C$7,0) -> 0 | H34: =IF(H23=$C$6,$C$7,0) -> 0 | I34: =IF(I23=$C$6,$C$7,0) -> 0 | J34: =IF(J23=$C$6,$C$7,0) -> 0 | ... V34: =IF(V23=$C$6,$C$7,0) -> 0
A35: Working Capital | C35: =IF(C23=$C$6,($C$13+SUM($C$48:$V$48))*$C$15,0) -> 0 | D35: =IF(D23=$C$6,($C$13+SUM($C$48:$V$48))*$C$15,0) -> 0 | E35: =IF(E23=$C$6,($C$13+SUM($C$48:$V$48))*$C$15,0) -> 0 | F35: =IF(F23=$C$6,($C$13+SUM($C$48:$V$48))*$C$15,0) -> 0 | G35: =IF(G23=$C$6,($C$13+SUM($C$48:$V$48))*$C$15,0) -> 0 | H35: =IF(H23=$C$6,($C$13+SUM($C$48:$V$48))*$C$15,0) -> 0 | I35: =IF(I23=$C$6,($C$13+SUM($C$48:$V$48))*$C$15,0) -> 0 | J35: =IF(J23=$C$6,($C$13+SUM($C$48:$V$48))*$C$15,0) -> 0 | ... V35: =IF(V23=$C$6,($C$13+SUM($C$48:$V$48))*$C$15,0) -> 0
A37: OPERATING CASHFLOWS
A38: Lifetime Index | C38: =IF(C23>$C$6,0,1) -> 1 | D38: =IF(D23>$C$6,0,1) -> 1 | E38: =IF(E23>$C$6,0,1) -> 1 | F38: =IF(F23>$C$6,0,1) -> 1 | G38: =IF(G23>$C$6,0,1) -> 1 | H38: =IF(H23>$C$6,0,1) -> 1 | I38: =IF(I23>$C$6,0,1) -> 1 | J38: =IF(J23>$C$6,0,1) -> 1 | ... V38: =IF(V23>$C$6,0,1) -> 0
A39: Revenues | C39: =G4 -> #REF! | D39: =C39*(1+D19)*D38 -> #REF! | E39: =D39*(1+E19)*E38 -> #REF! | F39: =E39*(1+F19)*F38 -> #REF! | G39: =F39*(1+G19)*G38 -> #REF! | H39: =G39*(1+H19)*H38 -> #REF! | I39: =H39*(1+I19)*I38 -> #REF! | J39: =I39*(1+J19)*J38 -> #REF! | K39: =J39*(1+K19)*K38 -> #REF! | ... V39: =U39*(1+V19)*V38 -> #REF!
A40: -Var. Expenses | C40: =C39*$G$5 -> #REF! | D40: =D39*$G$5 -> #REF! | E40: =E39*$G$5 -> #REF! | F40: =F39*$G$5 -> #REF! | G40: =G39*$G$5 -> #REF! | H40: =H39*$G$5 -> #REF! | I40: =I39*$G$5 -> #REF! | J40: =J39*$G$5 -> #REF! | ... V40: =V39*$G$5 -> #REF!
A41: - Fixed Expenses | C41: =G6 -> #REF! | D41: =C41*(1+D20)*D38 -> #REF! | E41: =D41*(1+E20)*E38 -> #REF! | F41: =E41*(1+F20)*F38 -> #REF! | G41: =F41*(1+G20)*G38 -> #REF! | H41: =G41*(1+H20)*H38 -> #REF! | I41: =H41*(1+I20)*I38 -> #REF! | J41: =I41*(1+J20)*J38 -> #REF! | K41: =J41*(1+K20)*K38 -> #REF! | ... V41: =U41*(1+V20)*V38 -> #REF!
A42: EBITDA | C42: =C39-C40-C41 -> #REF! | D42: =D39-D40-D41 -> #REF! | E42: =E39-E40-E41 -> #REF! | F42: =F39-F40-F41 -> #REF! | G42: =G39-G40-G41 -> #REF! | H42: =H39-H40-H41 -> #REF! | I42: =I39-I40-I41 -> #REF! | J42: =J39-J40-J41 -> #REF! | ... V42: =V39-V40-V41 -> #REF!
A43: - Depreciation | C43: =C61 -> #REF! | D43: =D61 -> #REF! | E43: =E61 -> #REF! | F43: =F61 -> #REF! | G43: =G61 -> #REF! | H43: =H61 -> #REF! | I43: =I61 -> #REF! | J43: =J61 -> #REF! | ... V43: =V61 -> #REF!
A44: EBIT | C44: =C42-C43 -> #REF! | D44: =D42-D43 -> #REF! | E44: =E42-E43 -> #REF! | F44: =F42-F43 -> #REF! | G44: =G42-G43 -> #REF! | H44: =H42-H43 -> #REF! | I44: =I42-I43 -> #REF! | J44: =J42-J43 -> #REF! | ... V44: =V42-V43 -> #REF!
A45: -Tax | C45: =C44*$G$7 -> #REF! | D45: =D44*$G$7 -> #REF! | E45: =E44*$G$7 -> #REF! | F45: =F44*$G$7 -> #REF! | G45: =G44*$G$7 -> #REF! | H45: =H44*$G$7 -> #REF! | I45: =I44*$G$7 -> #REF! | J45: =J44*$G$7 -> #REF! | ... V45: =V44*$G$7 -> #REF!
A46: EBT(1-t) | C46: =C44-C45 -> #REF! | D46: =D44-D45 -> #REF! | E46: =E44-E45 -> #REF! | F46: =F44-F45 -> #REF! | G46: =G44-G45 -> #REF! | H46: =H44-H45 -> #REF! | I46: =I44-I45 -> #REF! | J46: =J44-J45 -> #REF! | ... V46: =V44-V45 -> #REF!
A47: + Depreciation | C47: =C43 -> #REF! | D47: =D43 -> #REF! | E47: =E43 -> #REF! | F47: =F43 -> #REF! | G47: =G43 -> #REF! | H47: =H43 -> #REF! | I47: =I43 -> #REF! | J47: =J43 -> #REF! | ... V47: =V43 -> #REF!
A48: - ∂ Work. Cap | C48: =(C14*C39-B28)*C38 -> #REF! | D48: =($C$14*D39-$B$28)*D38 -> #REF! | E48: =($C$14*E39-$B$28)*E38 -> #REF! | F48: =($C$14*F39-$B$28)*F38 -> #REF! | G48: =($C$14*G39-$B$28)*G38 -> #REF! | H48: =($C$14*H39-$B$28)*H38 -> #REF! | I48: =($C$14*I39-$B$28)*I38 -> #REF! | J48: =($C$14*J39-$B$28)*J38 -> #REF! | K48: =($C$14*K39-$B$28)*K38 -> #REF! | ... V48: =($C$14*V39-$B$28)*V38 -> #REF!
A49: NATCF | B49: =0-B31 -> #REF! | C49: =C46+C47-C48 -> #REF! | D49: =D46+D47-D48 -> #REF! | E49: =E46+E47-E48 -> #REF! | F49: =F46+F47-F48 -> #REF! | G49: =G46+G47-G48 -> #REF! | H49: =H46+H47-H48 -> #REF! | I49: =I46+I47-I48 -> #REF! | J49: =J46+J47-J48 -> #REF! | ... V49: =V46+V47-V48 -> #REF!
A50: Discount Factor | B50: =1 -> 1 | C50: =C38*(1+$K$11)^C23 -> #REF! | D50: =D38*(1+$K$11)^D23 -> #REF! | E50: =E38*(1+$K$11)^E23 -> #REF! | F50: =F38*(1+$K$11)^F23 -> #REF! | G50: =G38*(1+$K$11)^G23 -> #REF! | H50: =H38*(1+$K$11)^H23 -> #REF! | I50: =I38*(1+$K$11)^I23 -> #REF! | J50: =J38*(1+$K$11)^J23 -> #REF! | ... V50: =V38*(1+$K$11)^V23 -> #REF!
A51: Discounted CF | B51: =0-B31 -> #REF! | C51: =(C49+C34+C35)/(1+$K$11)^C23 -> #REF! | D51: =(D49+D34+D35)/(1+$K$11)^D23 -> #REF! | E51: =(E49+E34+E35)/(1+$K$11)^E23 -> #REF! | F51: =(F49+F34+F35)/(1+$K$11)^F23 -> #REF! | G51: =(G49+G34+G35)/(1+$K$11)^G23 -> #REF! | H51: =(H49+H34+H35)/(1+$K$11)^H23 -> #REF! | I51: =(I49+I34+I35)/(1+$K$11)^I23 -> #REF! | J51: =(J49+J34+J35)/(1+$K$11)^J23 -> #REF! | ... V51: =(V49+V34+V35)/(1+$K$11)^V23 -> #REF!
B53: Investment Measures
B54: NPV = | C54: =SUM(B51:V51) -> #REF!
B55: IRR = | C55: =IRR(B49:V49,K11) -> #REF!
B56: ROC = | C56: =SUM(C46:V46)/SUM(B62:V62) -> #REF!
E59: BOOK VALUE & DEPRECIATION
A60: Book Value (beginning) | C60: =C4 -> #REF! | D60: =(C60-C61)*D38 -> #REF! | E60: =(D60-D61)*E38 -> #REF! | F60: =(E60-E61)*F38 -> #REF! | G60: =(F60-F61)*G38 -> #REF! | H60: =(G60-G61)*H38 -> #REF! | I60: =(H60-H61)*I38 -> #REF! | J60: =(I60-I61)*J38 -> #REF! | K60: =(J60-J61)*K38 -> #REF! | ... V60: =(U60-U61)*V38 -> #REF!
A61: Depreciation | C61: =IF($C$8=1,(($C$4-$C$7)/$C$6)*C38,(IF($C$7<$C$4*(1-2/$C$6)^(C23),$C$4*(1-2/$C$6)^(C23-1)*(2/$C$6)*C38,(IF(0>($C$4*(1-2/$C$6)^(C23-1))-$C$7,0,$C$4*C38*(1-2/$C$6)^(C23-1)-$C$7))))) -> #REF! | D61: =IF($C$8=1,(($C$4-$C$7)/$C$6)*D38,(IF($C$7<$C$4*(1-2/$C$6)^(D23),$C$4*(1-2/$C$6)^(D23-1)*(2/$C$6)*D38,(IF(0>($C$4*(1-2/$C$6)^(D23-1))-$C$7,0,$C$4*D38*(1-2/$C$6)^(D23-1)-$C$7))))) -> #REF! | E61: =IF($C$8=1,(($C$4-$C$7)/$C$6)*E38,(IF($C$7<$C$4*(1-2/$C$6)^(E23),$C$4*(1-2/$C$6)^(E23-1)*(2/$C$6)*E38,(IF(0>($C$4*(1-2/$C$6)^(E23-1))-$C$7,0,$C$4*E38*(1-2/$C$6)^(E23-1)-$C$7))))) -> #REF! | F61: =IF($C$8=1,(($C$4-$C$7)/$C$6)*F38,(IF($C$7<$C$4*(1-2/$C$6)^(F23),$C$4*(1-2/$C$6)^(F23-1)*(2/$C$6)*F38,(IF(0>($C$4*(1-2/$C$6)^(F23-1))-$C$7,0,$C$4*F38*(1-2/$C$6)^(F23-1)-$C$7))))) -> #REF! | G61: =IF($C$8=1,(($C$4-$C$7)/$C$6)*G38,(IF($C$7<$C$4*(1-2/$C$6)^(G23),$C$4*(1-2/$C$6)^(G23-1)*(2/$C$6)*G38,(IF(0>($C$4*(1-2/$C$6)^(G23-1))-$C$7,0,$C$4*G38*(1-2/$C$6)^(G23-1)-$C$7))))) -> #REF! | H61: =IF($C$8=1,(($C$4-$C$7)/$C$6)*H38,(IF($C$7<$C$4*(1-2/$C$6)^(H23),$C$4*(1-2/$C$6)^(H23-1)*(2/$C$6)*H38,(IF(0>($C$4*(1-2/$C$6)^(H23-1))-$C$7,0,$C$4*H38*(1-2/$C$6)^(H23-1)-$C$7))))) -> #REF! | I61: =IF($C$8=1,(($C$4-$C$7)/$C$6)*I38,(IF($C$7<$C$4*(1-2/$C$6)^(I23),$C$4*(1-2/$C$6)^(I23-1)*(2/$C$6)*I38,(IF(0>($C$4*(1-2/$C$6)^(I23-1))-$C$7,0,$C$4*I38*(1-2/$C$6)^(I23-1)-$C$7))))) -> #REF! | J61: =IF($C$8=1,(($C$4-$C$7)/$C$6)*J38,(IF($C$7<$C$4*(1-2/$C$6)^(J23),$C$4*(1-2/$C$6)^(J23-1)*(2/$C$6)*J38,(IF(0>($C$4*(1-2/$C$6)^(J23-1))-$C$7,0,$C$4*J38*(1-2/$C$6)^(J23-1)-$C$7))))) -> #REF! | ... V61: =IF($C$8=1,(($C$4-$C$7)/$C$6)*V38,(IF($C$7<$C$4*(1-2/$C$6)^(V23),$C$4*(1-2/$C$6)^(V23-1)*(2/$C$6)*V38,(IF(0>($C$4*(1-2/$C$6)^(V23-1))-$C$7,0,$C$4*V38*(1-2/$C$6)^(V23-1)-$C$7))))) -> #REF!
A62: BV(ending) | B62: =C4 -> #REF! | C62: =C60-C61 -> #REF! | D62: =D60-D61 -> #REF! | E62: =E60-E61 -> #REF! | F62: =F60-F61 -> #REF! | G62: =G60-G61 -> #REF! | H62: =H60-H61 -> #REF! | I62: =I60-I61 -> #REF! | J62: =J60-J61 -> #REF! | ... V62: =V60-V61 -> #REF!
